{
"meta":{"test_sets":[],"test_metrics":[],"learn_metrics":[{"best_value":"Min","name":"RMSE"}],"launch_mode":"Train","parameters":"","iteration_count":1000,"learn_sets":["learn"],"name":"experiment"},
"iterations":[
{"learn":[14.59871775],"iteration":0,"passed_time":0.0613733671,"remaining_time":61.31199373},
{"learn":[14.22518863],"iteration":1,"passed_time":0.06175891133,"remaining_time":30.81769675},
{"learn":[13.8866124],"iteration":2,"passed_time":0.0621689974,"remaining_time":20.66083013},
{"learn":[13.52356875],"iteration":3,"passed_time":0.06245958266,"remaining_time":15.55243608},
{"learn":[13.18870211],"iteration":4,"passed_time":0.06279187654,"remaining_time":12.49558343},
{"learn":[12.9124226],"iteration":5,"passed_time":0.06312217041,"remaining_time":10.45723956},
{"learn":[12.60003351],"iteration":6,"passed_time":0.06344408922,"remaining_time":8.999997228},
{"learn":[12.32990573],"iteration":7,"passed_time":0.06377329975,"remaining_time":7.907889169},
{"learn":[12.0660619],"iteration":8,"passed_time":0.06406688504,"remaining_time":7.054475897},
{"learn":[11.77309809],"iteration":9,"passed_time":0.06439051219,"remaining_time":6.374660707},
{"learn":[11.49227636],"iteration":10,"passed_time":0.06473559782,"remaining_time":5.82031875},
{"learn":[11.26264833],"iteration":11,"passed_time":0.0649971829,"remaining_time":5.351434725},
{"learn":[11.04260393],"iteration":12,"passed_time":0.06537522708,"remaining_time":4.963488395},
{"learn":[10.79916926],"iteration":13,"passed_time":0.06566060398,"remaining_time":4.624382538},
{"learn":[10.5541002],"iteration":14,"passed_time":0.06593923084,"remaining_time":4.330009492},
{"learn":[10.31918115],"iteration":15,"passed_time":0.06620235759,"remaining_time":4.071444992},
{"learn":[10.10004441],"iteration":16,"passed_time":0.06643231746,"remaining_time":3.841351062},
{"learn":[9.894556723],"iteration":17,"passed_time":0.06684057018,"remaining_time":3.64652444},
{"learn":[9.690174082],"iteration":18,"passed_time":0.06715911396,"remaining_time":3.467531095},
{"learn":[9.506034866],"iteration":19,"passed_time":0.06744244919,"remaining_time":3.30468001},
{"learn":[9.338524633],"iteration":20,"passed_time":0.0677300761,"remaining_time":3.157511643},
{"learn":[9.170203312],"iteration":21,"passed_time":0.06799411953,"remaining_time":3.022647677},
{"learn":[9.010299969],"iteration":22,"passed_time":0.06825407959,"remaining_time":2.899314598},
{"learn":[8.843866678],"iteration":23,"passed_time":0.06860487359,"remaining_time":2.789931526},
{"learn":[8.690548059],"iteration":24,"passed_time":0.06897016769,"remaining_time":2.68983654},
{"learn":[8.555307687],"iteration":25,"passed_time":0.06927016969,"remaining_time":2.594967126},
{"learn":[8.413851302],"iteration":26,"passed_time":0.06954700487,"remaining_time":2.50626799},
{"learn":[8.29256019],"iteration":27,"passed_time":0.06982121503,"remaining_time":2.423793607},
{"learn":[8.162193833],"iteration":28,"passed_time":0.07017250903,"remaining_time":2.349569182},
{"learn":[8.040736294],"iteration":29,"passed_time":0.07042521905,"remaining_time":2.277082083},
{"learn":[7.921220278],"iteration":30,"passed_time":0.07066501231,"remaining_time":2.208851514},
{"learn":[7.809589039],"iteration":31,"passed_time":0.07094618085,"remaining_time":2.146121971},
{"learn":[7.699675801],"iteration":32,"passed_time":0.07121526598,"remaining_time":2.086823097},
{"learn":[7.60645267],"iteration":33,"passed_time":0.07153176809,"remaining_time":2.032343764},
{"learn":[7.498880302],"iteration":34,"passed_time":0.07188485377,"remaining_time":1.981968111},
{"learn":[7.401158744],"iteration":35,"passed_time":0.07223123108,"remaining_time":1.934191854},
{"learn":[7.306431077],"iteration":36,"passed_time":0.07259848353,"remaining_time":1.889522693},
{"learn":[7.223863468],"iteration":37,"passed_time":0.07288748545,"remaining_time":1.845204237},
{"learn":[7.143477682],"iteration":38,"passed_time":0.07314682051,"remaining_time":1.80241268},
{"learn":[7.062817131],"iteration":39,"passed_time":0.07344457249,"remaining_time":1.76266974},
{"learn":[6.990793435],"iteration":40,"passed_time":0.0738104916,"remaining_time":1.726445401},
{"learn":[6.931862224],"iteration":41,"passed_time":0.07419961919,"remaining_time":1.692457981},
{"learn":[6.858296558],"iteration":42,"passed_time":0.07455416322,"remaining_time":1.659263586},
{"learn":[6.786268161],"iteration":43,"passed_time":0.07483379008,"remaining_time":1.625934166},
{"learn":[6.717118549],"iteration":44,"passed_time":0.07524470948,"remaining_time":1.596859946},
{"learn":[6.652948106],"iteration":45,"passed_time":0.07562037865,"remaining_time":1.568300896},
{"learn":[6.589686076],"iteration":46,"passed_time":0.07599929784,"remaining_time":1.541007039},
{"learn":[6.531283097],"iteration":47,"passed_time":0.07637063365,"remaining_time":1.514684234},
{"learn":[6.471368031],"iteration":48,"passed_time":0.07669730249,"remaining_time":1.488553769},
{"learn":[6.416481395],"iteration":49,"passed_time":0.07700713789,"remaining_time":1.46313562},
{"learn":[6.369870822],"iteration":50,"passed_time":0.07735747356,"remaining_time":1.439455733},
{"learn":[6.325678067],"iteration":51,"passed_time":0.07773193438,"remaining_time":1.417112958},
{"learn":[6.275766122],"iteration":52,"passed_time":0.07800643621,"remaining_time":1.393813115},
{"learn":[6.224773967],"iteration":53,"passed_time":0.0783155216,"remaining_time":1.371971915},
{"learn":[6.182249254],"iteration":54,"passed_time":0.07865394052,"remaining_time":1.351417705},
{"learn":[6.139904173],"iteration":55,"passed_time":0.07896252591,"remaining_time":1.33108258},
{"learn":[6.100525536],"iteration":56,"passed_time":0.0792465278,"remaining_time":1.311043434},
{"learn":[6.062568564],"iteration":57,"passed_time":0.07965740554,"remaining_time":1.293746138},
{"learn":[6.030559288],"iteration":58,"passed_time":0.07996753261,"remaining_time":1.275414376},
{"learn":[5.997931376],"iteration":59,"passed_time":0.08026953462,"remaining_time":1.257556042},
{"learn":[5.964103835],"iteration":60,"passed_time":0.08054811981,"remaining_time":1.239912861},
{"learn":[5.933729724],"iteration":61,"passed_time":0.08086295524,"remaining_time":1.223378258},
{"learn":[5.901932711],"iteration":62,"passed_time":0.08124120776,"remaining_time":1.208301772},
{"learn":[5.873727795],"iteration":63,"passed_time":0.08151679292,"remaining_time":1.192183097},
{"learn":[5.846485734],"iteration":64,"passed_time":0.08177962801,"remaining_time":1.176368495},
{"learn":[5.820630862],"iteration":65,"passed_time":0.08216646392,"remaining_time":1.162779959},
{"learn":[5.793646238],"iteration":66,"passed_time":0.08248846606,"remaining_time":1.148682669},
{"learn":[5.765388646],"iteration":67,"passed_time":0.08281367656,"remaining_time":1.135034508},
{"learn":[5.747073912],"iteration":68,"passed_time":0.08315780385,"remaining_time":1.122027759},
{"learn":[5.722315217],"iteration":69,"passed_time":0.08352743132,"remaining_time":1.109721587},
{"learn":[5.699970599],"iteration":70,"passed_time":0.08381243321,"remaining_time":1.096644373},
{"learn":[5.682732647],"iteration":71,"passed_time":0.08406372655,"remaining_time":1.083488031},
{"learn":[5.663525791],"iteration":72,"passed_time":0.08431597823,"remaining_time":1.070697422},
{"learn":[5.642381613],"iteration":73,"passed_time":0.08471423089,"remaining_time":1.060072673},
{"learn":[5.621404779],"iteration":74,"passed_time":0.08503202467,"remaining_time":1.048728304},
{"learn":[5.602460129],"iteration":75,"passed_time":0.08537848531,"remaining_time":1.038022637},
{"learn":[5.587337574],"iteration":76,"passed_time":0.08572857098,"remaining_time":1.027629494},
{"learn":[5.572393026],"iteration":77,"passed_time":0.08601136453,"remaining_time":1.016698437},
{"learn":[5.558425806],"iteration":78,"passed_time":0.08629394974,"remaining_time":1.006034528},
{"learn":[5.541518902],"iteration":79,"passed_time":0.08666991058,"remaining_time":0.9967039717},
{"learn":[5.526157283],"iteration":80,"passed_time":0.08700632949,"remaining_time":0.9871458864},
{"learn":[5.511746977],"iteration":81,"passed_time":0.08736345686,"remaining_time":0.9780445537},
{"learn":[5.504975022],"iteration":82,"passed_time":0.08746883257,"remaining_time":0.9663725237},
{"learn":[5.493980522],"iteration":83,"passed_time":0.08773470934,"remaining_time":0.9567261161},
{"learn":[5.480745463],"iteration":84,"passed_time":0.08800054444,"remaining_time":0.9472999784},
{"learn":[5.464052013],"iteration":85,"passed_time":0.08828233798,"remaining_time":0.9382564758},
{"learn":[5.449143727],"iteration":86,"passed_time":0.08872313259,"remaining_time":0.9310829891},
{"learn":[5.438255432],"iteration":87,"passed_time":0.0891098435,"remaining_time":0.9235020144},
{"learn":[5.425927931],"iteration":88,"passed_time":0.08941276218,"remaining_time":0.9152250151},
{"learn":[5.412331217],"iteration":89,"passed_time":0.08968797235,"remaining_time":0.9068450537},
{"learn":[5.400691499],"iteration":90,"passed_time":0.0900714749,"remaining_time":0.8997249526},
{"learn":[5.391618744],"iteration":91,"passed_time":0.09045085243,"remaining_time":0.892710587},
{"learn":[5.380766572],"iteration":92,"passed_time":0.09074864608,"remaining_time":0.8850432472},
{"learn":[5.372207183],"iteration":93,"passed_time":0.09105598146,"remaining_time":0.8776246723},
{"learn":[5.362918837],"iteration":94,"passed_time":0.09146856754,"remaining_time":0.8713584592},
{"learn":[5.348292324],"iteration":95,"passed_time":0.09178173629,"remaining_time":0.8642780167},
{"learn":[5.339772295],"iteration":96,"passed_time":0.09204323803,"remaining_time":0.8568561231},
{"learn":[5.331515983],"iteration":97,"passed_time":0.09235690679,"remaining_time":0.8500605094},
{"learn":[5.323861644],"iteration":98,"passed_time":0.09264757539,"remaining_time":0.8431865195},
{"learn":[5.313277281],"iteration":99,"passed_time":0.09297699425,"remaining_time":0.8367929483},
{"learn":[5.30685627],"iteration":100,"passed_time":0.09330695478,"remaining_time":0.8305242807},
{"learn":[5.29652059],"iteration":101,"passed_time":0.09358970667,"remaining_time":0.8239564371},
{"learn":[5.288350766],"iteration":102,"passed_time":0.09383916666,"remaining_time":0.8172207038},
{"learn":[5.27993346],"iteration":103,"passed_time":0.09412696024,"remaining_time":0.8109399652},
{"learn":[5.271789139],"iteration":104,"passed_time":0.09449792105,"remaining_time":0.8054822794},
{"learn":[5.262684686],"iteration":105,"passed_time":0.09479417302,"remaining_time":0.7994904781},
{"learn":[5.251619772],"iteration":106,"passed_time":0.09515013373,"remaining_time":0.7941034525},
{"learn":[5.241012171],"iteration":107,"passed_time":0.09540584376,"remaining_time":0.7879815985},
{"learn":[5.232684032],"iteration":108,"passed_time":0.09563359528,"remaining_time":0.7817388385},
{"learn":[5.224267141],"iteration":109,"passed_time":0.09585476342,"remaining_time":0.7755521768},
{"learn":[5.216324968],"iteration":110,"passed_time":0.09617997392,"remaining_time":0.7703062776},
{"learn":[5.211102527],"iteration":111,"passed_time":0.09653197626,"remaining_time":0.7653606689},
{"learn":[5.206364257],"iteration":112,"passed_time":0.09688760363,"remaining_time":0.7605248179},
{"learn":[5.196937641],"iteration":113,"passed_time":0.09725385607,"remaining_time":0.7558501445},
{"learn":[5.190746047],"iteration":114,"passed_time":0.09759423334,"remaining_time":0.7510512739},
{"learn":[5.181885213],"iteration":115,"passed_time":0.09788798529,"remaining_time":0.7459739569},
{"learn":[5.178293568],"iteration":116,"passed_time":0.09805215305,"remaining_time":0.7400004372},
{"learn":[5.170991438],"iteration":117,"passed_time":0.09838911363,"remaining_time":0.7354169341},
{"learn":[5.166257212],"iteration":118,"passed_time":0.09876928283,"remaining_time":0.7312246905},
{"learn":[5.161421246],"iteration":119,"passed_time":0.09913411859,"remaining_time":0.7269835364},
{"learn":[5.158223542],"iteration":120,"passed_time":0.09948253758,"remaining_time":0.7226871945},
{"learn":[5.15470988],"iteration":121,"passed_time":0.09972916422,"remaining_time":0.7177230015},
{"learn":[5.146388143],"iteration":122,"passed_time":0.1000967083,"remaining_time":0.7136976684},
{"learn":[5.139529364],"iteration":123,"passed_time":0.1004738358,"remaining_time":0.7097990339},
{"learn":[5.134276023],"iteration":124,"passed_time":0.1007351293,"remaining_time":0.7051459048},
{"learn":[5.128536065],"iteration":125,"passed_time":0.1010385896,"remaining_time":0.7008549787},
{"learn":[5.123300353],"iteration":126,"passed_time":0.1012646745,"remaining_time":0.6960949669},
{"learn":[5.116200518],"iteration":127,"passed_time":0.1015847182,"remaining_time":0.6920458931},
{"learn":[5.108728704],"iteration":128,"passed_time":0.1019520957,"remaining_time":0.6883742275},
{"learn":[5.104075866],"iteration":129,"passed_time":0.1023139731,"remaining_time":0.6847165892},
{"learn":[5.100317606],"iteration":130,"passed_time":0.1026371419,"remaining_time":0.6808524911},
{"learn":[5.095814182],"iteration":131,"passed_time":0.1029415606,"remaining_time":0.6769187471},
{"learn":[5.092146915],"iteration":132,"passed_time":0.1032096874,"remaining_time":0.6728029998},
{"learn":[5.085258329],"iteration":133,"passed_time":0.1034814809,"remaining_time":0.6687683764},
{"learn":[5.079219421],"iteration":134,"passed_time":0.1037891496,"remaining_time":0.6650193659},
{"learn":[5.076476829],"iteration":135,"passed_time":0.1041669854,"remaining_time":0.6617667311},
{"learn":[5.072133867],"iteration":136,"passed_time":0.1044332789,"remaining_time":0.6578534283},
{"learn":[5.067031564],"iteration":137,"passed_time":0.1047381559,"remaining_time":0.6542339884},
{"learn":[5.061358312],"iteration":138,"passed_time":0.1051087834,"remaining_time":0.6510695144},
{"learn":[5.056759124],"iteration":139,"passed_time":0.1054414939,"remaining_time":0.6477120342},
{"learn":[5.050254],"iteration":140,"passed_time":0.1057196625,"remaining_time":0.6440651777},
{"learn":[5.048376474],"iteration":141,"passed_time":0.1059266638,"remaining_time":0.6400357575},
{"learn":[5.042603751],"iteration":142,"passed_time":0.1063208748,"remaining_time":0.6371817461},
{"learn":[5.037477349],"iteration":143,"passed_time":0.1065942933,"remaining_time":0.6336438545},
{"learn":[5.03230489],"iteration":144,"passed_time":0.1068609617,"remaining_time":0.6301111881},
{"learn":[5.025976187],"iteration":145,"passed_time":0.1071044217,"remaining_time":0.6264875076},
{"learn":[5.01952451],"iteration":146,"passed_time":0.1073522567,"remaining_time":0.6229352036},
{"learn":[5.017569424],"iteration":147,"passed_time":0.1076229251,"remaining_time":0.6195590014},
{"learn":[5.008962367],"iteration":148,"passed_time":0.1079214271,"remaining_time":0.6163834529},
{"learn":[5.003880266],"iteration":149,"passed_time":0.1082735545,"remaining_time":0.613550142},
{"learn":[4.996387564],"iteration":150,"passed_time":0.1086113484,"remaining_time":0.6106691045},
{"learn":[4.993361683],"iteration":151,"passed_time":0.108854475,"remaining_time":0.6072933868},
{"learn":[4.99005752],"iteration":152,"passed_time":0.109260061,"remaining_time":0.6048579849},
{"learn":[4.986908764],"iteration":153,"passed_time":0.1095308128,"remaining_time":0.6017082316},
{"learn":[4.985207175],"iteration":154,"passed_time":0.1098308565,"remaining_time":0.5987553145},
{"learn":[4.979003494],"iteration":155,"passed_time":0.1101471086,"remaining_time":0.5959241004},
{"learn":[4.973142217],"iteration":156,"passed_time":0.1104083603,"remaining_time":0.5928296037},
{"learn":[4.967056696],"iteration":157,"passed_time":0.1106921956,"remaining_time":0.5898913207},
{"learn":[4.961460696],"iteration":158,"passed_time":0.1110431979,"remaining_time":0.5873416946},
{"learn":[4.954240363],"iteration":159,"passed_time":0.1113313665,"remaining_time":0.5844896741},
{"learn":[4.952320707],"iteration":160,"passed_time":0.1114766591,"remaining_time":0.5809249504},
{"learn":[4.948337777],"iteration":161,"passed_time":0.1118334948,"remaining_time":0.5784967202},
{"learn":[4.943228639],"iteration":162,"passed_time":0.1121251635,"remaining_time":0.5757592749},
{"learn":[4.938545759],"iteration":163,"passed_time":0.1124851658,"remaining_time":0.5733999918},
{"learn":[4.935330572],"iteration":164,"passed_time":0.1128402932,"remaining_time":0.5710402717},
{"learn":[4.932051543],"iteration":165,"passed_time":0.1131323368,"remaining_time":0.5683877645},
{"learn":[4.928964153],"iteration":166,"passed_time":0.1134329222,"remaining_time":0.5658061327},
{"learn":[4.922860227],"iteration":167,"passed_time":0.1137987579,"remaining_time":0.5635748012},
{"learn":[4.917668772],"iteration":168,"passed_time":0.1141260934,"remaining_time":0.5611762346},
{"learn":[4.910365386],"iteration":169,"passed_time":0.1144410539,"remaining_time":0.558741616},
{"learn":[4.906457206],"iteration":170,"passed_time":0.1147810978,"remaining_time":0.5564533923},
{"learn":[4.901996508],"iteration":171,"passed_time":0.1150953916,"remaining_time":0.5540638617},
{"learn":[4.896816173],"iteration":172,"passed_time":0.1154428939,"remaining_time":0.5518570707},
{"learn":[4.891123132],"iteration":173,"passed_time":0.1157958129,"remaining_time":0.5496973647},
{"learn":[4.887630202],"iteration":174,"passed_time":0.1161239401,"remaining_time":0.5474414318},
{"learn":[4.885259712],"iteration":175,"passed_time":0.1164871508,"remaining_time":0.5453716607},
{"learn":[4.880659728],"iteration":176,"passed_time":0.1168106113,"remaining_time":0.5431363453},
{"learn":[4.877299723],"iteration":177,"passed_time":0.117068238,"remaining_time":0.5406184925},
{"learn":[4.874038772],"iteration":178,"passed_time":0.1173241981,"remaining_time":0.5381182493},
{"learn":[4.86943698],"iteration":179,"passed_time":0.1176253668,"remaining_time":0.535848893},
{"learn":[4.861268711],"iteration":180,"passed_time":0.117965994,"remaining_time":0.5337798293},
{"learn":[4.858673056],"iteration":181,"passed_time":0.1182420792,"remaining_time":0.5314396746},
{"learn":[4.854036207],"iteration":182,"passed_time":0.118515581,"remaining_time":0.5291105447},
{"learn":[4.85130244],"iteration":183,"passed_time":0.118809833,"remaining_time":0.526895781},
{"learn":[4.847510084],"iteration":184,"passed_time":0.119118335,"remaining_time":0.524764557},
{"learn":[4.845691673],"iteration":185,"passed_time":0.1194780874,"remaining_time":0.5228772213},
{"learn":[4.842058646],"iteration":186,"passed_time":0.119763881,"remaining_time":0.5206846805},
{"learn":[4.838623675],"iteration":187,"passed_time":0.1200676747,"remaining_time":0.5185901694},
{"learn":[4.834602161],"iteration":188,"passed_time":0.1203523849,"remaining_time":0.5164327204},
{"learn":[4.830858976],"iteration":189,"passed_time":0.1206508036,"remaining_time":0.5143534257},
{"learn":[4.827590511],"iteration":190,"passed_time":0.1209797224,"remaining_time":0.5124219657},
{"learn":[4.822246226],"iteration":191,"passed_time":0.1213169747,"remaining_time":0.5105422684},
{"learn":[4.816686395],"iteration":192,"passed_time":0.1216463102,"remaining_time":0.5086454525},
{"learn":[4.814797121],"iteration":193,"passed_time":0.1219052286,"remaining_time":0.5064722384},
{"learn":[4.811639392],"iteration":194,"passed_time":0.1221941472,"remaining_time":0.504442505},
{"learn":[4.804813432],"iteration":195,"passed_time":0.1224481489,"remaining_time":0.5022873046},
{"learn":[4.80251613],"iteration":196,"passed_time":0.1228063596,"remaining_time":0.5005761764},
{"learn":[4.800087884],"iteration":197,"passed_time":0.1231899038,"remaining_time":0.4989813276},
{"learn":[4.794773135],"iteration":198,"passed_time":0.1234866558,"remaining_time":0.4970493029},
{"learn":[4.791664833],"iteration":199,"passed_time":0.1237448658,"remaining_time":0.4949794634},
{"learn":[4.785989873],"iteration":200,"passed_time":0.1240066176,"remaining_time":0.4929417286},
{"learn":[4.782387142],"iteration":201,"passed_time":0.1243782867,"remaining_time":0.491355806},
{"learn":[4.778623704],"iteration":202,"passed_time":0.1246489135,"remaining_time":0.4893851433},
{"learn":[4.775772178],"iteration":203,"passed_time":0.1249064569,"remaining_time":0.4873800966},
{"learn":[4.77023101],"iteration":204,"passed_time":0.1251807504,"remaining_time":0.4854570564},
{"learn":[4.764496689],"iteration":205,"passed_time":0.1254502105,"remaining_time":0.483531394},
{"learn":[4.763138716],"iteration":206,"passed_time":0.1257113373,"remaining_time":0.481589809},
{"learn":[4.758053283],"iteration":207,"passed_time":0.1259423388,"remaining_time":0.4795496747},
{"learn":[4.755063788],"iteration":208,"passed_time":0.1262005489,"remaining_time":0.4776298285},
{"learn":[4.752465267],"iteration":209,"passed_time":0.1265129676,"remaining_time":0.4759297353},
{"learn":[4.748067377],"iteration":210,"passed_time":0.1269209287,"remaining_time":0.4746000603},
{"learn":[4.744163298],"iteration":211,"passed_time":0.1272539309,"remaining_time":0.4730004601},
{"learn":[4.736670896],"iteration":212,"passed_time":0.1275793497,"remaining_time":0.4713847334},
{"learn":[4.73349255],"iteration":213,"passed_time":0.1278597266,"remaining_time":0.4696156313},
{"learn":[4.731864595],"iteration":214,"passed_time":0.1281057699,"remaining_time":0.4677350203},
{"learn":[4.728398311],"iteration":215,"passed_time":0.1284380221,"remaining_time":0.4661824506},
{"learn":[4.723865975],"iteration":216,"passed_time":0.1287156073,"remaining_time":0.4644438733},
{"learn":[4.723483365],"iteration":217,"passed_time":0.1289791507,"remaining_time":0.4626683296},
{"learn":[4.72095416],"iteration":218,"passed_time":0.1292547775,"remaining_time":0.4609496861},
{"learn":[4.716173382],"iteration":219,"passed_time":0.1295019042,"remaining_time":0.4591431148},
{"learn":[4.710563974],"iteration":220,"passed_time":0.1298569482,"remaining_time":0.4577310528},
{"learn":[4.707160263],"iteration":221,"passed_time":0.1302059089,"remaining_time":0.4563071942},
{"learn":[4.70408351],"iteration":222,"passed_time":0.1305238693,"remaining_time":0.4547849617},
{"learn":[4.702501831],"iteration":223,"passed_time":0.1307937878,"remaining_time":0.4531070506},
{"learn":[4.700269738],"iteration":224,"passed_time":0.1311061649,"remaining_time":0.4515879012},
{"learn":[4.695346302],"iteration":225,"passed_time":0.1314430004,"remaining_time":0.4501631962},
{"learn":[4.689769299],"iteration":226,"passed_time":0.1317642526,"remaining_time":0.4486950099},
{"learn":[4.687919514],"iteration":227,"passed_time":0.1321225466,"remaining_time":0.447362307},
{"learn":[4.682982074],"iteration":228,"passed_time":0.1324549239,"remaining_time":0.4459508572},
{"learn":[4.679578702],"iteration":229,"passed_time":0.1328027178,"remaining_time":0.4446004032},
{"learn":[4.675751423],"iteration":230,"passed_time":0.1331315117,"remaining_time":0.4431953788},
{"learn":[4.672710726],"iteration":231,"passed_time":0.1335001391,"remaining_time":0.4419314951},
{"learn":[4.6690533],"iteration":232,"passed_time":0.13387235,"remaining_time":0.4406870919},
{"learn":[4.667595702],"iteration":233,"passed_time":0.134282686,"remaining_time":0.4395749466},
{"learn":[4.664241291],"iteration":234,"passed_time":0.1346192299,"remaining_time":0.438228557},
{"learn":[4.662246999],"iteration":235,"passed_time":0.134981774,"remaining_time":0.4369748955},
{"learn":[4.658668443],"iteration":236,"passed_time":0.1352781927,"remaining_time":0.4355158692},
{"learn":[4.658017572],"iteration":237,"passed_time":0.1356194033,"remaining_time":0.4342100222},
{"learn":[4.657656705],"iteration":238,"passed_time":0.1358675299,"remaining_time":0.4326158589},
{"learn":[4.653242871],"iteration":239,"passed_time":0.1361983238,"remaining_time":0.431294692},
{"learn":[4.6507302],"iteration":240,"passed_time":0.1365427011,"remaining_time":0.4300245233},
{"learn":[4.647671336],"iteration":241,"passed_time":0.1368370364,"remaining_time":0.4286052627},
{"learn":[4.645506007],"iteration":242,"passed_time":0.1371022881,"remaining_time":0.4271046589},
{"learn":[4.641297906],"iteration":243,"passed_time":0.1374611655,"remaining_time":0.425904267},
{"learn":[4.63798107],"iteration":244,"passed_time":0.1377827093,"remaining_time":0.4245956961},
{"learn":[4.635062318],"iteration":245,"passed_time":0.1380430027,"remaining_time":0.4231074149},
{"learn":[4.631606017],"iteration":246,"passed_time":0.1383414631,"remaining_time":0.4217454319},
{"learn":[4.630215494],"iteration":247,"passed_time":0.1386137565,"remaining_time":0.4203126811},
{"learn":[4.62729814],"iteration":248,"passed_time":0.1388874667,"remaining_time":0.418893524},
{"learn":[4.624691756],"iteration":249,"passed_time":0.1392000521,"remaining_time":0.4176001563},
{"learn":[4.621840053],"iteration":250,"passed_time":0.1394678039,"remaining_time":0.4161808172},
{"learn":[4.619602091],"iteration":251,"passed_time":0.1397772643,"remaining_time":0.4148944194},
{"learn":[4.613584029],"iteration":252,"passed_time":0.1401080165,"remaining_time":0.41367861},
{"learn":[4.6119388],"iteration":253,"passed_time":0.1404601022,"remaining_time":0.4125324261},
{"learn":[4.60870702],"iteration":254,"passed_time":0.140833938,"remaining_time":0.4114560149},
{"learn":[4.604771557],"iteration":255,"passed_time":0.1412768159,"remaining_time":0.4105857463},
{"learn":[4.604231277],"iteration":256,"passed_time":0.1415891097,"remaining_time":0.4093412782},
{"learn":[4.600750354],"iteration":257,"passed_time":0.141934862,"remaining_time":0.408200262},
{"learn":[4.596488253],"iteration":258,"passed_time":0.1422040721,"remaining_time":0.4068463994},
{"learn":[4.59470784],"iteration":259,"passed_time":0.1425232826,"remaining_time":0.4056431889},
{"learn":[4.588818005],"iteration":260,"passed_time":0.1428197846,"remaining_time":0.4043824551},
{"learn":[4.585054174],"iteration":261,"passed_time":0.1430624112,"remaining_time":0.4029773261},
{"learn":[4.581471435],"iteration":262,"passed_time":0.1433287463,"remaining_time":0.4016474753},
{"learn":[4.577555199],"iteration":263,"passed_time":0.1436787903,"remaining_time":0.4005590517},
{"learn":[4.57457145],"iteration":264,"passed_time":0.144039001,"remaining_time":0.399504399},
{"learn":[4.573029224],"iteration":265,"passed_time":0.1443668365,"remaining_time":0.3983656316},
{"learn":[4.571326203],"iteration":266,"passed_time":0.1447471724,"remaining_time":0.3973770688},
{"learn":[4.571019224],"iteration":267,"passed_time":0.1451220916,"remaining_time":0.3963782501},
{"learn":[4.565766631],"iteration":268,"passed_time":0.1454825523,"remaining_time":0.3953447796},
{"learn":[4.563383471],"iteration":269,"passed_time":0.1457403457,"remaining_time":0.3940387124},
{"learn":[4.558165805],"iteration":270,"passed_time":0.1460105141,"remaining_time":0.3927736709},
{"learn":[4.55629209],"iteration":271,"passed_time":0.1463764749,"remaining_time":0.3917723299},
{"learn":[4.549383848],"iteration":272,"passed_time":0.1466398933,"remaining_time":0.3905025731},
{"learn":[4.546227503],"iteration":273,"passed_time":0.1469438537,"remaining_time":0.3893475831},
{"learn":[4.540620977],"iteration":274,"passed_time":0.1472745642,"remaining_time":0.3882693057},
{"learn":[4.532898237],"iteration":275,"passed_time":0.1476089414,"remaining_time":0.3872060638},
{"learn":[4.529757367],"iteration":276,"passed_time":0.1479114435,"remaining_time":0.3860648867},
{"learn":[4.52579294],"iteration":277,"passed_time":0.1481573201,"remaining_time":0.3847826803},
{"learn":[4.521572155],"iteration":278,"passed_time":0.1485435727,"remaining_time":0.3838706663},
{"learn":[4.518818099],"iteration":279,"passed_time":0.1488138245,"remaining_time":0.3826641201},
{"learn":[4.514012334],"iteration":280,"passed_time":0.1491160348,"remaining_time":0.3815460108},
{"learn":[4.508331416],"iteration":281,"passed_time":0.1494771622,"remaining_time":0.3805836967},
{"learn":[4.506038537],"iteration":282,"passed_time":0.1498680815,"remaining_time":0.3797011111},
{"learn":[4.505805643],"iteration":283,"passed_time":0.1502505424,"remaining_time":0.3788006632},
{"learn":[4.501550352],"iteration":284,"passed_time":0.150691462,"remaining_time":0.3780505099},
{"learn":[4.494692643],"iteration":285,"passed_time":0.151043756,"remaining_time":0.377081265},
{"learn":[4.489330245],"iteration":286,"passed_time":0.1514128001,"remaining_time":0.376157932},
{"learn":[4.484826955],"iteration":287,"passed_time":0.1517790526,"remaining_time":0.3752315466},
{"learn":[4.478285428],"iteration":288,"passed_time":0.1521824719,"remaining_time":0.3744004759},
{"learn":[4.475311671],"iteration":289,"passed_time":0.1525591411,"remaining_time":0.3735068627},
{"learn":[4.471581298],"iteration":290,"passed_time":0.1529554771,"remaining_time":0.372664719},
{"learn":[4.469164956],"iteration":291,"passed_time":0.1532587707,"remaining_time":0.3716000332},
{"learn":[4.462068024],"iteration":292,"passed_time":0.15364869,"remaining_time":0.3707495694},
{"learn":[4.458540976],"iteration":293,"passed_time":0.1539557754,"remaining_time":0.3697033246},
{"learn":[4.455757458],"iteration":294,"passed_time":0.1543902783,"remaining_time":0.3689665972},
{"learn":[4.453027414],"iteration":295,"passed_time":0.1547624891,"remaining_time":0.3680837578},
{"learn":[4.450659338],"iteration":296,"passed_time":0.1550392826,"remaining_time":0.3669785039},
{"learn":[4.444696901],"iteration":297,"passed_time":0.1553373263,"remaining_time":0.3659288692},
{"learn":[4.442052813],"iteration":298,"passed_time":0.1556335366,"remaining_time":0.3648799636},
{"learn":[4.440036756],"iteration":299,"passed_time":0.1558847049,"remaining_time":0.3637309781},
{"learn":[4.435017051],"iteration":300,"passed_time":0.1562820825,"remaining_time":0.362927494},
{"learn":[4.429962125],"iteration":301,"passed_time":0.1566877519,"remaining_time":0.3621458637},
{"learn":[4.427666256],"iteration":302,"passed_time":0.1569787122,"remaining_time":0.3611028462},
{"learn":[4.425030004],"iteration":303,"passed_time":0.1572754642,"remaining_time":0.3600780364},
{"learn":[4.422588771],"iteration":304,"passed_time":0.1575676328,"remaining_time":0.3590475567},
{"learn":[4.418936667],"iteration":305,"passed_time":0.157895135,"remaining_time":0.3581020381},
{"learn":[4.416887976],"iteration":306,"passed_time":0.1582790125,"remaining_time":0.3572878035},
{"learn":[4.413773354],"iteration":307,"passed_time":0.1585653894,"remaining_time":0.3562573035},
{"learn":[4.411129391],"iteration":308,"passed_time":0.1588936416,"remaining_time":0.3553252633},
{"learn":[4.40850819],"iteration":309,"passed_time":0.1591763518,"remaining_time":0.3542957508},
{"learn":[4.404880292],"iteration":310,"passed_time":0.1594645204,"remaining_time":0.3532831336},
{"learn":[4.404593827],"iteration":311,"passed_time":0.1597662724,"remaining_time":0.3523051135},
{"learn":[4.402139942],"iteration":312,"passed_time":0.160096358,"remaining_time":0.3513936036},
{"learn":[4.400284725],"iteration":313,"passed_time":0.1604547353,"remaining_time":0.3505476065},
{"learn":[4.395805521],"iteration":314,"passed_time":0.1608266961,"remaining_time":0.349734244},
{"learn":[4.392838833],"iteration":315,"passed_time":0.1612316155,"remaining_time":0.3489950159},
{"learn":[4.389213061],"iteration":316,"passed_time":0.1615689511,"remaining_time":0.3481122826},
{"learn":[4.3861981],"iteration":317,"passed_time":0.1618724948,"remaining_time":0.3471605077},
{"learn":[4.385054234],"iteration":318,"passed_time":0.1622289972,"remaining_time":0.3463258529},
{"learn":[4.379364607],"iteration":319,"passed_time":0.1626233748,"remaining_time":0.3455746714},
{"learn":[4.378387619],"iteration":320,"passed_time":0.1629602937,"remaining_time":0.3447041726},
{"learn":[4.375816727],"iteration":321,"passed_time":0.1632638374,"remaining_time":0.3437667135},
{"learn":[4.374600202],"iteration":322,"passed_time":0.1635428809,"remaining_time":0.3427818278},
{"learn":[4.37098897],"iteration":323,"passed_time":0.1638359662,"remaining_time":0.3418305961},
{"learn":[4.367418484],"iteration":324,"passed_time":0.1641429266,"remaining_time":0.3409122321},
{"learn":[4.363584638],"iteration":325,"passed_time":0.1644334702,"remaining_time":0.3399636776},
{"learn":[4.360770706],"iteration":326,"passed_time":0.1647759308,"remaining_time":0.3391259982},
{"learn":[4.358675808],"iteration":327,"passed_time":0.1650820578,"remaining_time":0.338216899},
{"learn":[4.354228195],"iteration":328,"passed_time":0.1653687264,"remaining_time":0.3372717794},
{"learn":[4.353773425],"iteration":329,"passed_time":0.1656440616,"remaining_time":0.3363076402},
{"learn":[4.351648009],"iteration":330,"passed_time":0.165959522,"remaining_time":0.335428762},
{"learn":[4.348209927],"iteration":331,"passed_time":0.1662727741,"remaining_time":0.3345488346},
{"learn":[4.345852733],"iteration":332,"passed_time":0.1666213181,"remaining_time":0.3337430005},
{"learn":[4.34237339],"iteration":333,"passed_time":0.1668958616,"remaining_time":0.3327923467},
{"learn":[4.340814362],"iteration":334,"passed_time":0.1672132387,"remaining_time":0.3319307574},
{"learn":[4.339707068],"iteration":335,"passed_time":0.1674599487,"remaining_time":0.3309327557},
{"learn":[4.335430786],"iteration":336,"passed_time":0.1677112837,"remaining_time":0.3299483118},
{"learn":[4.33521887],"iteration":337,"passed_time":0.1679323268,"remaining_time":0.3289088768},
{"learn":[4.328507238],"iteration":338,"passed_time":0.1681708284,"remaining_time":0.3279083114},
{"learn":[4.326140732],"iteration":339,"passed_time":0.1683978299,"remaining_time":0.3268899051},
{"learn":[4.323785636],"iteration":340,"passed_time":0.1686266648,"remaining_time":0.3258796835},
{"learn":[4.320632534],"iteration":341,"passed_time":0.1689640837,"remaining_time":0.3250829446},
{"learn":[4.31973724],"iteration":342,"passed_time":0.1692285438,"remaining_time":0.3241491349},
{"learn":[4.318000924],"iteration":343,"passed_time":0.1694589203,"remaining_time":0.3231542201},
{"learn":[4.312713628],"iteration":344,"passed_time":0.1696910885,"remaining_time":0.3221671391},
{"learn":[4.308220789],"iteration":345,"passed_time":0.1699224234,"remaining_time":0.3211828465},
{"learn":[4.305890947],"iteration":346,"passed_time":0.1702026336,"remaining_time":0.3202948696},
{"learn":[4.305137856],"iteration":347,"passed_time":0.1704938855,"remaining_time":0.3194310729},
{"learn":[4.304787172],"iteration":348,"passed_time":0.1707579706,"remaining_time":0.3185198822},
{"learn":[4.30350134],"iteration":349,"passed_time":0.1710222224,"remaining_time":0.3176126987},
{"learn":[4.30293809],"iteration":350,"passed_time":0.1712971826,"remaining_time":0.3167289786},
{"learn":[4.299548459],"iteration":351,"passed_time":0.1715531426,"remaining_time":0.3158137398},
{"learn":[4.294768408],"iteration":352,"passed_time":0.1718261861,"remaining_time":0.3149335479},
{"learn":[4.294581479],"iteration":353,"passed_time":0.1720703544,"remaining_time":0.314004093},
{"learn":[4.292551604],"iteration":354,"passed_time":0.1723086893,"remaining_time":0.3130679003},
{"learn":[4.288628894],"iteration":355,"passed_time":0.1725570659,"remaining_time":0.3121537934},
{"learn":[4.287802767],"iteration":356,"passed_time":0.172810151,"remaining_time":0.3112518966},
{"learn":[4.284566905],"iteration":357,"passed_time":0.173061986,"remaining_time":0.3103513827},
{"learn":[4.27890232],"iteration":358,"passed_time":0.1733021126,"remaining_time":0.309433577},
{"learn":[4.276938023],"iteration":359,"passed_time":0.1735451559,"remaining_time":0.3085247215},
{"learn":[4.273425094],"iteration":360,"passed_time":0.173809991,"remaining_time":0.307658128},
{"learn":[4.269726505],"iteration":361,"passed_time":0.1740575343,"remaining_time":0.3067643836},
{"learn":[4.265565857],"iteration":362,"passed_time":0.1743010776,"remaining_time":0.3058671802},
{"learn":[4.262117173],"iteration":363,"passed_time":0.1745429958,"remaining_time":0.304970729},
{"learn":[4.259185148],"iteration":364,"passed_time":0.1748161643,"remaining_time":0.3041322311},
{"learn":[4.257668507],"iteration":365,"passed_time":0.1750805411,"remaining_time":0.303281593},
{"learn":[4.253432436],"iteration":366,"passed_time":0.175324626,"remaining_time":0.3023991506},
{"learn":[4.250216667],"iteration":367,"passed_time":0.1755680443,"remaining_time":0.3015190327},
{"learn":[4.24514828],"iteration":368,"passed_time":0.1757990459,"remaining_time":0.3006211326},
{"learn":[4.244015772],"iteration":369,"passed_time":0.1760495892,"remaining_time":0.2997601113},
{"learn":[4.240329192],"iteration":370,"passed_time":0.1763121326,"remaining_time":0.2989227262},
{"learn":[4.236718014],"iteration":371,"passed_time":0.1765788011,"remaining_time":0.2980953953},
{"learn":[4.233495944],"iteration":372,"passed_time":0.176821011,"remaining_time":0.2972299568},
{"learn":[4.230357491],"iteration":373,"passed_time":0.1770688877,"remaining_time":0.296377336},
{"learn":[4.227381215],"iteration":374,"passed_time":0.1773218477,"remaining_time":0.2955364128},
{"learn":[4.226169067],"iteration":375,"passed_time":0.1775758077,"remaining_time":0.2947002766},
{"learn":[4.225963861],"iteration":376,"passed_time":0.1778087676,"remaining_time":0.2938325257},
{"learn":[4.224346548],"iteration":377,"passed_time":0.1780663943,"remaining_time":0.2930087229},
{"learn":[4.222595381],"iteration":378,"passed_time":0.1782981458,"remaining_time":0.2921455107},
{"learn":[4.219700938],"iteration":379,"passed_time":0.1785604809,"remaining_time":0.2913355215},
{"learn":[4.216356207],"iteration":380,"passed_time":0.1788039409,"remaining_time":0.2904977412},
{"learn":[4.214326494],"iteration":381,"passed_time":0.1790387341,"remaining_time":0.2896490515},
{"learn":[4.212901398],"iteration":382,"passed_time":0.1793052776,"remaining_time":0.2888547161},
{"learn":[4.211331091],"iteration":383,"passed_time":0.1795618209,"remaining_time":0.2880470877},
{"learn":[4.208624791],"iteration":384,"passed_time":0.1797968642,"remaining_time":0.2872079778},
{"learn":[4.204659106],"iteration":385,"passed_time":0.1800385741,"remaining_time":0.2863826023},
{"learn":[4.202968852],"iteration":386,"passed_time":0.1803456178,"remaining_time":0.2856637305},
{"learn":[4.197261935],"iteration":387,"passed_time":0.1805855777,"remaining_time":0.284841169},
{"learn":[4.196934403],"iteration":388,"passed_time":0.1808201626,"remaining_time":0.2840131603},
{"learn":[4.192479929],"iteration":389,"passed_time":0.1810896228,"remaining_time":0.2832427433},
{"learn":[4.190243116],"iteration":390,"passed_time":0.1813421245,"remaining_time":0.2824484752},
{"learn":[4.185852431],"iteration":391,"passed_time":0.1815777927,"remaining_time":0.2816308621},
{"learn":[4.180967944],"iteration":392,"passed_time":0.181825711,"remaining_time":0.2808351313},
{"learn":[4.178283162],"iteration":393,"passed_time":0.1820835877,"remaining_time":0.2800574979},
{"learn":[4.176341157],"iteration":394,"passed_time":0.1823423811,"remaining_time":0.2792839002},
{"learn":[4.176041504],"iteration":395,"passed_time":0.1825727993,"remaining_time":0.2784696232},
{"learn":[4.175564513],"iteration":396,"passed_time":0.1828170926,"remaining_time":0.2776793623},
{"learn":[4.170830274],"iteration":397,"passed_time":0.1830853444,"remaining_time":0.2769280837},
{"learn":[4.167804808],"iteration":398,"passed_time":0.1833332627,"remaining_time":0.2761485987},
{"learn":[4.165860548],"iteration":399,"passed_time":0.1835684726,"remaining_time":0.2753527089},
{"learn":[4.160950571],"iteration":400,"passed_time":0.1837851407,"remaining_time":0.2745319184},
{"learn":[4.158544115],"iteration":401,"passed_time":0.1840178089,"remaining_time":0.2737379347},
{"learn":[4.154448767],"iteration":402,"passed_time":0.1842681856,"remaining_time":0.2729729697},
{"learn":[4.15197457],"iteration":403,"passed_time":0.1845418124,"remaining_time":0.272244852},
{"learn":[4.149562679],"iteration":404,"passed_time":0.1847906891,"remaining_time":0.2714826173},
{"learn":[4.149327961],"iteration":405,"passed_time":0.1851096079,"remaining_time":0.2708253869},
{"learn":[4.147444889],"iteration":406,"passed_time":0.1853511095,"remaining_time":0.2700570219},
{"learn":[4.147254809],"iteration":407,"passed_time":0.1855895694,"remaining_time":0.2692868262},
{"learn":[4.144589165],"iteration":408,"passed_time":0.1858520712,"remaining_time":0.2685539708},
{"learn":[4.141691034],"iteration":409,"passed_time":0.1861040312,"remaining_time":0.26780824},
{"learn":[4.138893468],"iteration":410,"passed_time":0.1864101999,"remaining_time":0.2671425979},
{"learn":[4.136964597],"iteration":411,"passed_time":0.18667941,"remaining_time":0.2664259541},
{"learn":[4.133773523],"iteration":412,"passed_time":0.1869603702,"remaining_time":0.2657281775},
{"learn":[4.131363444],"iteration":413,"passed_time":0.1872075802,"remaining_time":0.2649846425},
{"learn":[4.130228592],"iteration":414,"passed_time":0.1874421234,"remaining_time":0.2642256439},
{"learn":[4.12884186],"iteration":415,"passed_time":0.1876630416,"remaining_time":0.2634500391},
{"learn":[4.12413494],"iteration":416,"passed_time":0.1878845014,"remaining_time":0.262677852},
{"learn":[4.119422508],"iteration":417,"passed_time":0.1881471698,"remaining_time":0.2619656766},
{"learn":[4.117038244],"iteration":418,"passed_time":0.1883910047,"remaining_time":0.2612295316},
{"learn":[4.116067631],"iteration":419,"passed_time":0.1886078812,"remaining_time":0.2604585026},
{"learn":[4.110343455],"iteration":420,"passed_time":0.1888407994,"remaining_time":0.2597121683},
{"learn":[4.105604544],"iteration":421,"passed_time":0.1890794677,"remaining_time":0.2589761429},
{"learn":[4.103390131],"iteration":422,"passed_time":0.1892990108,"remaining_time":0.2582163811},
{"learn":[4.096724402],"iteration":423,"passed_time":0.1896198879,"remaining_time":0.2575968289},
{"learn":[4.093431279],"iteration":424,"passed_time":0.1898605145,"remaining_time":0.2568701079},
{"learn":[4.091412744],"iteration":425,"passed_time":0.1901081412,"remaining_time":0.256155101},
{"learn":[4.091192901],"iteration":426,"passed_time":0.1903638929,"remaining_time":0.2554531865},
{"learn":[4.088994581],"iteration":427,"passed_time":0.1905998528,"remaining_time":0.2547269061},
{"learn":[4.087845355],"iteration":428,"passed_time":0.1908535211,"remaining_time":0.2540264815},
{"learn":[4.083650279],"iteration":429,"passed_time":0.1910704809,"remaining_time":0.2532794747},
{"learn":[4.079840652],"iteration":430,"passed_time":0.1913132742,"remaining_time":0.2525690325},
{"learn":[4.075707828],"iteration":431,"passed_time":0.1915940677,"remaining_time":0.2519107187},
{"learn":[4.071345409],"iteration":432,"passed_time":0.1918486111,"remaining_time":0.2512197748},
{"learn":[4.067460475],"iteration":433,"passed_time":0.1920826543,"remaining_time":0.2505041068},
{"learn":[4.064914749],"iteration":434,"passed_time":0.1922964891,"remaining_time":0.2497644054},
{"learn":[4.063823175],"iteration":435,"passed_time":0.1925424907,"remaining_time":0.2490687265},
{"learn":[4.058898471],"iteration":436,"passed_time":0.1927750756,"remaining_time":0.2483578205},
{"learn":[4.054120355],"iteration":437,"passed_time":0.1930178689,"remaining_time":0.2476621971},
{"learn":[4.052715901],"iteration":438,"passed_time":0.1932431621,"remaining_time":0.2469462731},
{"learn":[4.052114167],"iteration":439,"passed_time":0.193486997,"remaining_time":0.246256178},
{"learn":[4.051377267],"iteration":440,"passed_time":0.1937165402,"remaining_time":0.2455499909},
{"learn":[4.049275336],"iteration":441,"passed_time":0.1939468751,"remaining_time":0.2448469599},
{"learn":[4.047099198],"iteration":442,"passed_time":0.1942190019,"remaining_time":0.2441986096},
{"learn":[4.044348685],"iteration":443,"passed_time":0.1944913787,"remaining_time":0.243552267},
{"learn":[4.042822379],"iteration":444,"passed_time":0.194735172,"remaining_time":0.2428719561},
{"learn":[4.041258611],"iteration":445,"passed_time":0.194980882,"remaining_time":0.2421959834},
{"learn":[4.040044254],"iteration":446,"passed_time":0.1952048835,"remaining_time":0.2414950795},
{"learn":[4.036860137],"iteration":447,"passed_time":0.1954522601,"remaining_time":0.2408251062},
{"learn":[4.036372284],"iteration":448,"passed_time":0.1956785116,"remaining_time":0.2401310911},
{"learn":[4.03368231],"iteration":449,"passed_time":0.1959160549,"remaining_time":0.2394529559},
{"learn":[4.032439519],"iteration":450,"passed_time":0.1961511814,"remaining_time":0.2387738328},
{"learn":[4.032008634],"iteration":451,"passed_time":0.196383433,"remaining_time":0.2380931886},
{"learn":[4.030034932],"iteration":452,"passed_time":0.1966041844,"remaining_time":0.2374006377},
{"learn":[4.028173412],"iteration":453,"passed_time":0.1968447277,"remaining_time":0.2367339677},
{"learn":[4.023806097],"iteration":454,"passed_time":0.1970699375,"remaining_time":0.2360508043},
{"learn":[4.020239186],"iteration":455,"passed_time":0.1973492727,"remaining_time":0.2354342201},
{"learn":[4.017384838],"iteration":456,"passed_time":0.1975788159,"remaining_time":0.2347599498},
{"learn":[4.016468229],"iteration":457,"passed_time":0.1978126092,"remaining_time":0.234092651},
{"learn":[4.014530169],"iteration":458,"passed_time":0.198045944,"remaining_time":0.2334267009},
{"learn":[4.012884822],"iteration":459,"passed_time":0.1982633205,"remaining_time":0.232743898},
{"learn":[4.008924707],"iteration":460,"passed_time":0.1984712802,"remaining_time":0.2320521042},
{"learn":[4.008286778],"iteration":461,"passed_time":0.1986906983,"remaining_time":0.2313757483},
{"learn":[4.006444202],"iteration":462,"passed_time":0.1989313666,"remaining_time":0.2307260127},
{"learn":[4.003284363],"iteration":463,"passed_time":0.1991651598,"remaining_time":0.2300700984},
{"learn":[3.999811484],"iteration":464,"passed_time":0.1993959114,"remaining_time":0.2294125002},
{"learn":[3.997483319],"iteration":465,"passed_time":0.1996526214,"remaining_time":0.2287864803},
{"learn":[3.99708333],"iteration":466,"passed_time":0.1998901647,"remaining_time":0.2281401665},
{"learn":[3.995860263],"iteration":467,"passed_time":0.2001248329,"remaining_time":0.2274923314},
{"learn":[3.994131111],"iteration":468,"passed_time":0.2003681678,"remaining_time":0.2268560706},
{"learn":[3.993125499],"iteration":469,"passed_time":0.2006214612,"remaining_time":0.2262327116},
{"learn":[3.992954084],"iteration":470,"passed_time":0.2008752546,"remaining_time":0.2256114855},
{"learn":[3.990635743],"iteration":471,"passed_time":0.2011127145,"remaining_time":0.224973545},
{"learn":[3.986678254],"iteration":472,"passed_time":0.2013473827,"remaining_time":0.2243341875},
{"learn":[3.986393291],"iteration":473,"passed_time":0.2016024261,"remaining_time":0.2237191479},
{"learn":[3.986152671],"iteration":474,"passed_time":0.2018668445,"remaining_time":0.223115986},
{"learn":[3.985596662],"iteration":475,"passed_time":0.202091846,"remaining_time":0.2224708557},
{"learn":[3.983853457],"iteration":476,"passed_time":0.202389598,"remaining_time":0.2219072531},
{"learn":[3.983263928],"iteration":477,"passed_time":0.2026723082,"remaining_time":0.2213283366},
{"learn":[3.980067202],"iteration":478,"passed_time":0.2029281432,"remaining_time":0.2207214251},
{"learn":[3.978115407],"iteration":479,"passed_time":0.2031643115,"remaining_time":0.2200946708},
{"learn":[3.972661644],"iteration":480,"passed_time":0.2034011047,"remaining_time":0.2194702149},
{"learn":[3.969938254],"iteration":481,"passed_time":0.2036597314,"remaining_time":0.2188708317},
{"learn":[3.968211434],"iteration":482,"passed_time":0.2039057331,"remaining_time":0.2182593457},
{"learn":[3.966113368],"iteration":483,"passed_time":0.2041547347,"remaining_time":0.2176525684},
{"learn":[3.962246044],"iteration":484,"passed_time":0.2043906946,"remaining_time":0.217033418},
{"learn":[3.961319703],"iteration":485,"passed_time":0.2046467797,"remaining_time":0.2164371291},
{"learn":[3.96078191],"iteration":486,"passed_time":0.2048579477,"remaining_time":0.2157949224},
{"learn":[3.958913633],"iteration":487,"passed_time":0.205100991,"remaining_time":0.215187925},
{"learn":[3.957428286],"iteration":488,"passed_time":0.2053234092,"remaining_time":0.2145608632},
{"learn":[3.952641965],"iteration":489,"passed_time":0.205553869,"remaining_time":0.2139438229},
{"learn":[3.951486786],"iteration":490,"passed_time":0.2057895789,"remaining_time":0.2133337998},
{"learn":[3.94938344],"iteration":491,"passed_time":0.2060387056,"remaining_time":0.2127391513},
{"learn":[3.947297924],"iteration":492,"passed_time":0.2062678321,"remaining_time":0.2121253365},
{"learn":[3.946284886],"iteration":493,"passed_time":0.2065043337,"remaining_time":0.2115206333},
{"learn":[3.943288204],"iteration":494,"passed_time":0.2067490437,"remaining_time":0.210925792},
{"learn":[3.943076488],"iteration":495,"passed_time":0.2069746285,"remaining_time":0.210312929},
{"learn":[3.942347078],"iteration":496,"passed_time":0.2072310469,"remaining_time":0.2097328301},
{"learn":[3.940251541],"iteration":497,"passed_time":0.2074682568,"remaining_time":0.2091346685},
{"learn":[3.939011019],"iteration":498,"passed_time":0.2076958,"remaining_time":0.2085282481},
{"learn":[3.938760512],"iteration":499,"passed_time":0.2079347599,"remaining_time":0.2079347599},
{"learn":[3.934522727],"iteration":500,"passed_time":0.2081785532,"remaining_time":0.2073475011},
{"learn":[3.930091193],"iteration":501,"passed_time":0.2084019297,"remaining_time":0.2067413565},
{"learn":[3.927671752],"iteration":502,"passed_time":0.208650098,"remaining_time":0.20616123},
{"learn":[3.927280041],"iteration":503,"passed_time":0.2088852246,"remaining_time":0.2055695861},
{"learn":[3.925987561],"iteration":504,"passed_time":0.2091223511,"remaining_time":0.2049813145},
{"learn":[3.921645957],"iteration":505,"passed_time":0.2093655611,"remaining_time":0.2044003699},
{"learn":[3.920333743],"iteration":506,"passed_time":0.209604896,"remaining_time":0.2038169896},
{"learn":[3.918659461],"iteration":507,"passed_time":0.2098283975,"remaining_time":0.2032196291},
{"learn":[3.916124385],"iteration":508,"passed_time":0.2100482323,"remaining_time":0.2026202005},
{"learn":[3.913849268],"iteration":509,"passed_time":0.2102799422,"remaining_time":0.2020336699},
{"learn":[3.912826119],"iteration":510,"passed_time":0.2105095271,"remaining_time":0.2014464946},
{"learn":[3.910034145],"iteration":511,"passed_time":0.2107156118,"remaining_time":0.2008383175},
{"learn":[3.90792379],"iteration":512,"passed_time":0.2109474466,"remaining_time":0.200256153},
{"learn":[3.907823851],"iteration":513,"passed_time":0.2111860732,"remaining_time":0.1996817735},
{"learn":[3.904527401],"iteration":514,"passed_time":0.2114144081,"remaining_time":0.1990990057},
{"learn":[3.903378283],"iteration":515,"passed_time":0.211648118,"remaining_time":0.1985226533},
{"learn":[3.902170135],"iteration":516,"passed_time":0.211907953,"remaining_time":0.1979720335},
{"learn":[3.899435429],"iteration":517,"passed_time":0.2121530797,"remaining_time":0.1974088502},
{"learn":[3.897497505],"iteration":518,"passed_time":0.2123788312,"remaining_time":0.196828936},
{"learn":[3.896426119],"iteration":519,"passed_time":0.2126161661,"remaining_time":0.1962610764},
{"learn":[3.896044669],"iteration":520,"passed_time":0.2128386259,"remaining_time":0.1956808096},
{"learn":[3.892795942],"iteration":521,"passed_time":0.2130769192,"remaining_time":0.1951164126},
{"learn":[3.892413888],"iteration":522,"passed_time":0.2133300458,"remaining_time":0.1945667913},
{"learn":[3.891738985],"iteration":523,"passed_time":0.2135723808,"remaining_time":0.1940084986},
{"learn":[3.88822057],"iteration":524,"passed_time":0.2138177991,"remaining_time":0.1934541992},
{"learn":[3.883837053],"iteration":525,"passed_time":0.2140420089,"remaining_time":0.1928819624},
{"learn":[3.881769742],"iteration":526,"passed_time":0.2142788438,"remaining_time":0.1923223779},
{"learn":[3.880356898],"iteration":527,"passed_time":0.2145633874,"remaining_time":0.1918066645},
{"learn":[3.879250273],"iteration":528,"passed_time":0.2148252641,"remaining_time":0.1912716435},
{"learn":[3.877174493],"iteration":529,"passed_time":0.215051099,"remaining_time":0.1907056915},
{"learn":[3.875854201],"iteration":530,"passed_time":0.2152936422,"remaining_time":0.1901557782},
{"learn":[3.873189396],"iteration":531,"passed_time":0.2155254355,"remaining_time":0.1895975635},
{"learn":[3.871583368],"iteration":532,"passed_time":0.2157779788,"remaining_time":0.1890587544},
{"learn":[3.869622679],"iteration":533,"passed_time":0.2160020636,"remaining_time":0.1884961829},
{"learn":[3.866860164],"iteration":534,"passed_time":0.2162284401,"remaining_time":0.1879368685},
{"learn":[3.864498444],"iteration":535,"passed_time":0.2164952336,"remaining_time":0.1874137843},
{"learn":[3.861416322],"iteration":536,"passed_time":0.2167146517,"remaining_time":0.1868508077},
{"learn":[3.860265769],"iteration":537,"passed_time":0.2169929036,"remaining_time":0.1863396309},
{"learn":[3.859328725],"iteration":538,"passed_time":0.2172307385,"remaining_time":0.1857947504},
{"learn":[3.858521278],"iteration":539,"passed_time":0.2175016986,"remaining_time":0.1852792248},
{"learn":[3.85599111],"iteration":540,"passed_time":0.2177553253,"remaining_time":0.1847498971},
{"learn":[3.852379816],"iteration":541,"passed_time":0.2179912019,"remaining_time":0.1842065876},
{"learn":[3.851327537],"iteration":542,"passed_time":0.2182395369,"remaining_time":0.1836748957},
{"learn":[3.847854898],"iteration":543,"passed_time":0.2184707884,"remaining_time":0.1831299256},
{"learn":[3.847083414],"iteration":544,"passed_time":0.21870379,"remaining_time":0.1825875678},
{"learn":[3.845397429],"iteration":545,"passed_time":0.2189360832,"remaining_time":0.1820457541},
{"learn":[3.841933528],"iteration":546,"passed_time":0.2191974599,"remaining_time":0.1815291578},
{"learn":[3.840996474],"iteration":547,"passed_time":0.2194422949,"remaining_time":0.1809998491},
{"learn":[3.838355966],"iteration":548,"passed_time":0.2196803798,"remaining_time":0.1804660315},
{"learn":[3.83342799],"iteration":549,"passed_time":0.2199290481,"remaining_time":0.1799419485},
{"learn":[3.828161535],"iteration":550,"passed_time":0.2201575913,"remaining_time":0.1794024655},
{"learn":[3.823502399],"iteration":551,"passed_time":0.2203853845,"remaining_time":0.1788635005},
{"learn":[3.820068862],"iteration":552,"passed_time":0.2206458446,"remaining_time":0.178352066},
{"learn":[3.817951642],"iteration":553,"passed_time":0.2208744294,"remaining_time":0.1778158764},
{"learn":[3.815785958],"iteration":554,"passed_time":0.2211067643,"remaining_time":0.177283802},
{"learn":[3.81503012],"iteration":555,"passed_time":0.2213374742,"remaining_time":0.1767515081},
{"learn":[3.813529315],"iteration":556,"passed_time":0.2215545589,"remaining_time":0.1762094607},
{"learn":[3.808881326],"iteration":557,"passed_time":0.2217706854,"remaining_time":0.1756678189},
{"learn":[3.808740434],"iteration":558,"passed_time":0.222015187,"remaining_time":0.1751497271},
{"learn":[3.80714352],"iteration":559,"passed_time":0.2222472302,"remaining_time":0.1746228237},
{"learn":[3.80573346],"iteration":560,"passed_time":0.2224727734,"remaining_time":0.1740918851},
{"learn":[3.803370052],"iteration":561,"passed_time":0.2226973582,"remaining_time":0.1735612863},
{"learn":[3.803215211],"iteration":562,"passed_time":0.2229402765,"remaining_time":0.173046005},
{"learn":[3.801309667],"iteration":563,"passed_time":0.2231558613,"remaining_time":0.1725105594},
{"learn":[3.800003847],"iteration":564,"passed_time":0.2233897378,"remaining_time":0.1719903291},
{"learn":[3.798026138],"iteration":565,"passed_time":0.2236064893,"remaining_time":0.1714579794},
{"learn":[3.794745847],"iteration":566,"passed_time":0.2238608243,"remaining_time":0.1709554443},
{"learn":[3.794312041],"iteration":567,"passed_time":0.2241070759,"remaining_time":0.1704476352},
{"learn":[3.792205926],"iteration":568,"passed_time":0.2243381608,"remaining_time":0.1699292571},
{"learn":[3.788991061],"iteration":569,"passed_time":0.2245907042,"remaining_time":0.1694280751},
{"learn":[3.787391572],"iteration":570,"passed_time":0.2248201224,"remaining_time":0.1689103897},
{"learn":[3.7826445],"iteration":571,"passed_time":0.2250527489,"remaining_time":0.1683961128},
{"learn":[3.781700331],"iteration":572,"passed_time":0.2252907922,"remaining_time":0.1678868556},
{"learn":[3.780045374],"iteration":573,"passed_time":0.2254965435,"remaining_time":0.1673545776},
{"learn":[3.775462644],"iteration":574,"passed_time":0.2257307951,"remaining_time":0.1668445007},
{"learn":[3.773711943],"iteration":575,"passed_time":0.2259731717,"remaining_time":0.1663413625},
{"learn":[3.772415806],"iteration":576,"passed_time":0.2262161733,"remaining_time":0.1658395863},
{"learn":[3.770170875],"iteration":577,"passed_time":0.2264573416,"remaining_time":0.1653373671},
{"learn":[3.765166479],"iteration":578,"passed_time":0.2267141766,"remaining_time":0.164847441},
{"learn":[3.763976102],"iteration":579,"passed_time":0.2269567199,"remaining_time":0.1643479696},
{"learn":[3.760761708],"iteration":580,"passed_time":0.2271845131,"remaining_time":0.1638387453},
{"learn":[3.758155662],"iteration":581,"passed_time":0.2274328064,"remaining_time":0.1633452115},
{"learn":[3.756844548],"iteration":582,"passed_time":0.227669558,"remaining_time":0.1628442636},
{"learn":[3.753098923],"iteration":583,"passed_time":0.2279014762,"remaining_time":0.1623407776},
{"learn":[3.751618946],"iteration":584,"passed_time":0.2281328111,"remaining_time":0.1618378062},
{"learn":[3.751398464],"iteration":585,"passed_time":0.2283622293,"remaining_time":0.1613344077},
{"learn":[3.749920103],"iteration":586,"passed_time":0.2285779391,"remaining_time":0.1608222978},
{"learn":[3.748237465],"iteration":587,"passed_time":0.2288238157,"remaining_time":0.1603323334},
{"learn":[3.746021536],"iteration":588,"passed_time":0.2290847758,"remaining_time":0.159853723},
{"learn":[3.74417648],"iteration":589,"passed_time":0.2292888605,"remaining_time":0.1593363268},
{"learn":[3.738788389],"iteration":590,"passed_time":0.2295329038,"remaining_time":0.1588476441},
{"learn":[3.736021611],"iteration":591,"passed_time":0.2297593636,"remaining_time":0.1583476695},
{"learn":[3.734546151],"iteration":592,"passed_time":0.2299939068,"remaining_time":0.1578541654},
{"learn":[3.733527479],"iteration":593,"passed_time":0.2302324501,"remaining_time":0.1573642672},
{"learn":[3.733026392],"iteration":594,"passed_time":0.2304494515,"remaining_time":0.156860551},
{"learn":[3.730314752],"iteration":595,"passed_time":0.2306762864,"remaining_time":0.1563644626},
{"learn":[3.727342596],"iteration":596,"passed_time":0.2309636216,"remaining_time":0.1559101164},
{"learn":[3.725459604],"iteration":597,"passed_time":0.2312301234,"remaining_time":0.1554423237},
{"learn":[3.723158842],"iteration":598,"passed_time":0.2314854168,"remaining_time":0.1549676997},
{"learn":[3.722362756],"iteration":599,"passed_time":0.2317281684,"remaining_time":0.1544854456},
{"learn":[3.721443615],"iteration":600,"passed_time":0.23196842,"remaining_time":0.1540023287},
{"learn":[3.720743486],"iteration":601,"passed_time":0.2321896298,"remaining_time":0.1535074297},
{"learn":[3.720215334],"iteration":602,"passed_time":0.2324181313,"remaining_time":0.153018239},
{"learn":[3.719436563],"iteration":603,"passed_time":0.2327230917,"remaining_time":0.1525800402},
{"learn":[3.715046574],"iteration":604,"passed_time":0.2330093436,"remaining_time":0.1521300673},
{"learn":[3.71443396],"iteration":605,"passed_time":0.2332481785,"remaining_time":0.1516498058},
{"learn":[3.712938941],"iteration":606,"passed_time":0.2335034302,"remaining_time":0.1511809688},
{"learn":[3.712814764],"iteration":607,"passed_time":0.2337360984,"remaining_time":0.150698274},
{"learn":[3.71235348],"iteration":608,"passed_time":0.2339883501,"remaining_time":0.1502289735},
{"learn":[3.711223749],"iteration":609,"passed_time":0.2342403101,"remaining_time":0.1497601983},
{"learn":[3.710755648],"iteration":610,"passed_time":0.2344868951,"remaining_time":0.1492887106},
{"learn":[3.708668039],"iteration":611,"passed_time":0.2347186883,"remaining_time":0.1488085802},
{"learn":[3.705623591],"iteration":612,"passed_time":0.2349581482,"remaining_time":0.1483341001},
{"learn":[3.704045802],"iteration":613,"passed_time":0.2351940248,"remaining_time":0.1478581328},
{"learn":[3.699915209],"iteration":614,"passed_time":0.2354169846,"remaining_time":0.1473748603},
{"learn":[3.696182221],"iteration":615,"passed_time":0.2356588612,"remaining_time":0.1469042252},
{"learn":[3.694263278],"iteration":616,"passed_time":0.2359029045,"remaining_time":0.1464356765},
{"learn":[3.693810229],"iteration":617,"passed_time":0.2361490728,"remaining_time":0.145969168},
{"learn":[3.690900932],"iteration":618,"passed_time":0.2363770743,"remaining_time":0.1454921895},
{"learn":[3.688020895],"iteration":619,"passed_time":0.2366006592,"remaining_time":0.1450133072},
{"learn":[3.685491894],"iteration":620,"passed_time":0.236824619,"remaining_time":0.144535476},
{"learn":[3.684328128],"iteration":621,"passed_time":0.237033662,"remaining_time":0.1440493959},
{"learn":[3.680640153],"iteration":622,"passed_time":0.2372487051,"remaining_time":0.143567836},
{"learn":[3.678932783],"iteration":623,"passed_time":0.2374925401,"remaining_time":0.1431044793},
{"learn":[3.674167041],"iteration":624,"passed_time":0.23772225,"remaining_time":0.14263335},
{"learn":[3.672200976],"iteration":625,"passed_time":0.2379548348,"remaining_time":0.1421647096},
{"learn":[3.670606604],"iteration":626,"passed_time":0.238180878,"remaining_time":0.1416929306},
{"learn":[3.665506042],"iteration":627,"passed_time":0.2384090879,"remaining_time":0.1412232177},
{"learn":[3.664214007],"iteration":628,"passed_time":0.2386529228,"remaining_time":0.1407634887},
{"learn":[3.66261643],"iteration":629,"passed_time":0.238885841,"remaining_time":0.1402980336},
{"learn":[3.662118449],"iteration":630,"passed_time":0.2391067592,"remaining_time":0.1398262982},
{"learn":[3.660871366],"iteration":631,"passed_time":0.2393379274,"remaining_time":0.1393613248},
{"learn":[3.656695243],"iteration":632,"passed_time":0.239577679,"remaining_time":0.1389020666},
{"learn":[3.654497801],"iteration":633,"passed_time":0.2398152639,"remaining_time":0.1384422501},
{"learn":[3.654189134],"iteration":634,"passed_time":0.240037557,"remaining_time":0.1379743438},
{"learn":[3.653957699],"iteration":635,"passed_time":0.2402502668,"remaining_time":0.137501725},
{"learn":[3.651920725],"iteration":636,"passed_time":0.2404647266,"remaining_time":0.1370309195},
{"learn":[3.65106705],"iteration":637,"passed_time":0.2406896447,"remaining_time":0.1365668517},
{"learn":[3.650612844],"iteration":638,"passed_time":0.2409432714,"remaining_time":0.1361197511},
{"learn":[3.649884732],"iteration":639,"passed_time":0.2411598145,"remaining_time":0.1356523957},
{"learn":[3.646276182],"iteration":640,"passed_time":0.2413816077,"remaining_time":0.1351887631},
{"learn":[3.645808194],"iteration":641,"passed_time":0.2416133175,"remaining_time":0.1347314138},
{"learn":[3.645042989],"iteration":642,"passed_time":0.2418439857,"remaining_time":0.134274188},
{"learn":[3.639864499],"iteration":643,"passed_time":0.2420955291,"remaining_time":0.1338292055},
{"learn":[3.637318478],"iteration":644,"passed_time":0.2423418224,"remaining_time":0.1333819333},
{"learn":[3.636344905],"iteration":645,"passed_time":0.2426007408,"remaining_time":0.1329422016},
{"learn":[3.634754643],"iteration":646,"passed_time":0.2428441591,"remaining_time":0.1324945721},
{"learn":[3.630724975],"iteration":647,"passed_time":0.2430833273,"remaining_time":0.1320452642},
{"learn":[3.629408252],"iteration":648,"passed_time":0.2433386624,"remaining_time":0.1316053474},
{"learn":[3.62790646],"iteration":649,"passed_time":0.2435639972,"remaining_time":0.1311498446},
{"learn":[3.627388973],"iteration":650,"passed_time":0.2437805403,"remaining_time":0.1306903357},
{"learn":[3.625163557],"iteration":651,"passed_time":0.2440088335,"remaining_time":0.1302378436},
{"learn":[3.623701985],"iteration":652,"passed_time":0.2442625852,"remaining_time":0.1297995667},
{"learn":[3.622342639],"iteration":653,"passed_time":0.2445084618,"remaining_time":0.1293576878},
{"learn":[3.621130639],"iteration":654,"passed_time":0.2447608802,"remaining_time":0.1289198529},
{"learn":[3.619125665],"iteration":655,"passed_time":0.2450040485,"remaining_time":0.1284777327},
{"learn":[3.618878783],"iteration":656,"passed_time":0.2452550918,"remaining_time":0.1280403295},
{"learn":[3.616207429],"iteration":657,"passed_time":0.2455244686,"remaining_time":0.1276130217},
{"learn":[3.61206486],"iteration":658,"passed_time":0.2457496784,"remaining_time":0.1271633389},
{"learn":[3.611955873],"iteration":659,"passed_time":0.2459637215,"remaining_time":0.1267085838},
{"learn":[3.610713743],"iteration":660,"passed_time":0.2461764313,"remaining_time":0.1262538732},
{"learn":[3.610044025],"iteration":661,"passed_time":0.2464325163,"remaining_time":0.12582204},
{"learn":[3.607342669],"iteration":662,"passed_time":0.2466569761,"remaining_time":0.1253746621},
{"learn":[3.602510618],"iteration":663,"passed_time":0.2469183112,"remaining_time":0.1249466153},
{"learn":[3.600492392],"iteration":664,"passed_time":0.2472133965,"remaining_time":0.1245360719},
{"learn":[3.597171065],"iteration":665,"passed_time":0.2474579398,"remaining_time":0.1241005284},
{"learn":[3.594358798],"iteration":666,"passed_time":0.2477163582,"remaining_time":0.1236724847},
{"learn":[3.593945251],"iteration":667,"passed_time":0.2479484431,"remaining_time":0.1232318609},
{"learn":[3.593607748],"iteration":668,"passed_time":0.2481908197,"remaining_time":0.1227969526},
{"learn":[3.592238714],"iteration":669,"passed_time":0.248445488,"remaining_time":0.1223686732},
{"learn":[3.590144654],"iteration":670,"passed_time":0.2487301566,"remaining_time":0.1219556208},
{"learn":[3.587151536],"iteration":671,"passed_time":0.2489770333,"remaining_time":0.1215245043},
{"learn":[3.586070865],"iteration":672,"passed_time":0.2492192432,"remaining_time":0.1210916679},
{"learn":[3.585102746],"iteration":673,"passed_time":0.2494797033,"remaining_time":0.1206682244},
{"learn":[3.584362847],"iteration":674,"passed_time":0.2497324133,"remaining_time":0.1202415323},
{"learn":[3.581407561],"iteration":675,"passed_time":0.2499678732,"remaining_time":0.1198070871},
{"learn":[3.57919422],"iteration":676,"passed_time":0.2502267499,"remaining_time":0.1193844021},
{"learn":[3.577632204],"iteration":677,"passed_time":0.2504540431,"remaining_time":0.1189472004},
{"learn":[3.573911195],"iteration":678,"passed_time":0.2507031698,"remaining_time":0.1185209389},
{"learn":[3.573408216],"iteration":679,"passed_time":0.2509315463,"remaining_time":0.1180854335},
{"learn":[3.571076482],"iteration":680,"passed_time":0.2511668395,"remaining_time":0.1176537765},
{"learn":[3.568177107],"iteration":681,"passed_time":0.2514048411,"remaining_time":0.1172239582},
{"learn":[3.564824621],"iteration":682,"passed_time":0.2516569261,"remaining_time":0.116801238},
{"learn":[3.562475026],"iteration":683,"passed_time":0.2518845943,"remaining_time":0.1163677365},
{"learn":[3.561226889],"iteration":684,"passed_time":0.2521362626,"remaining_time":0.1159458726},
{"learn":[3.559383467],"iteration":685,"passed_time":0.2523785559,"remaining_time":0.1155202136},
{"learn":[3.555209766],"iteration":686,"passed_time":0.252637641,"remaining_time":0.1151027389},
{"learn":[3.55345383],"iteration":687,"passed_time":0.2528630175,"remaining_time":0.1146704382},
{"learn":[3.552300968],"iteration":688,"passed_time":0.2530849356,"remaining_time":0.114237177},
{"learn":[3.551253986],"iteration":689,"passed_time":0.2533200205,"remaining_time":0.113810444},
{"learn":[3.549807725],"iteration":690,"passed_time":0.253541272,"remaining_time":0.1133780797},
{"learn":[3.547992926],"iteration":691,"passed_time":0.2537700652,"remaining_time":0.1129496822},
{"learn":[3.545438607],"iteration":692,"passed_time":0.2540097751,"remaining_time":0.1125266969},
{"learn":[3.543313763],"iteration":693,"passed_time":0.2542247765,"remaining_time":0.1120933453},
{"learn":[3.542962896],"iteration":694,"passed_time":0.2545180285,"remaining_time":0.1116949621},
{"learn":[3.539800465],"iteration":695,"passed_time":0.2547459883,"remaining_time":0.1112683627},
{"learn":[3.53953187],"iteration":696,"passed_time":0.2549733649,"remaining_time":0.1108420797},
{"learn":[3.536332425],"iteration":697,"passed_time":0.2552392416,"remaining_time":0.1104330243},
{"learn":[3.534993327],"iteration":698,"passed_time":0.25549191,"remaining_time":0.1100186908},
{"learn":[3.531637011],"iteration":699,"passed_time":0.2557130365,"remaining_time":0.1095913013},
{"learn":[3.531040284],"iteration":700,"passed_time":0.255941038,"remaining_time":0.1091674327},
{"learn":[3.529973872],"iteration":701,"passed_time":0.2561718312,"remaining_time":0.1087453073},
{"learn":[3.527325183],"iteration":702,"passed_time":0.2564049577,"remaining_time":0.1083247119},
{"learn":[3.527200815],"iteration":703,"passed_time":0.2566367093,"remaining_time":0.1079040709},
{"learn":[3.523459911],"iteration":704,"passed_time":0.2568791692,"remaining_time":0.1074884467},
{"learn":[3.522729934],"iteration":705,"passed_time":0.2571267542,"remaining_time":0.1070754472},
{"learn":[3.522260582],"iteration":706,"passed_time":0.2573675058,"remaining_time":0.1066600837},
{"learn":[3.518641591],"iteration":707,"passed_time":0.257595674,"remaining_time":0.1062400237},
{"learn":[3.516856405],"iteration":708,"passed_time":0.2578285922,"remaining_time":0.1058224546},
{"learn":[3.515083413],"iteration":709,"passed_time":0.2580503854,"remaining_time":0.1054008616},
{"learn":[3.514671214],"iteration":710,"passed_time":0.2582684285,"remaining_time":0.1049783064},
{"learn":[3.512617621],"iteration":711,"passed_time":0.2584846799,"remaining_time":0.1045556009},
{"learn":[3.510747971],"iteration":712,"passed_time":0.2587357233,"remaining_time":0.1041474791},
{"learn":[3.508149266],"iteration":713,"passed_time":0.2589703915,"remaining_time":0.103733238},
{"learn":[3.504557165],"iteration":714,"passed_time":0.259197268,"remaining_time":0.1033163935},
{"learn":[3.501367208],"iteration":715,"passed_time":0.2594150611,"remaining_time":0.1028964768},
{"learn":[3.497593362],"iteration":716,"passed_time":0.2596376459,"remaining_time":0.1024790151},
{"learn":[3.496291169],"iteration":717,"passed_time":0.2598576057,"remaining_time":0.1020610652},
{"learn":[3.49330374],"iteration":718,"passed_time":0.260092149,"remaining_time":0.1016493656},
{"learn":[3.490044385],"iteration":719,"passed_time":0.2603133588,"remaining_time":0.1012329729},
{"learn":[3.488891789],"iteration":720,"passed_time":0.2605436936,"remaining_time":0.1008206526},
{"learn":[3.486869081],"iteration":721,"passed_time":0.2607784869,"remaining_time":0.1004105531},
{"learn":[3.486303638],"iteration":722,"passed_time":0.2610251552,"remaining_time":0.1000054882},
{"learn":[3.486035862],"iteration":723,"passed_time":0.261256115,"remaining_time":0.09959487258},
{"learn":[3.482668951],"iteration":724,"passed_time":0.2615311169,"remaining_time":0.09920145812},
{"learn":[3.47820549],"iteration":725,"passed_time":0.2617790352,"remaining_time":0.09879814827},
{"learn":[3.474392283],"iteration":726,"passed_time":0.2619848699,"remaining_time":0.09837946283},
{"learn":[3.472268163],"iteration":727,"passed_time":0.2622184548,"remaining_time":0.09797173036},
{"learn":[3.471209164],"iteration":728,"passed_time":0.2624584147,"remaining_time":0.09756684552},
{"learn":[3.470049971],"iteration":729,"passed_time":0.2627103747,"remaining_time":0.09716685092},
{"learn":[3.469078654],"iteration":730,"passed_time":0.262949168,"remaining_time":0.09676241612},
{"learn":[3.468643292],"iteration":731,"passed_time":0.2631898779,"remaining_time":0.09635913563},
{"learn":[3.468134848],"iteration":732,"passed_time":0.2634182128,"remaining_time":0.09595179101},
{"learn":[3.467820182],"iteration":733,"passed_time":0.2636436309,"remaining_time":0.09554387715},
{"learn":[3.465776156],"iteration":734,"passed_time":0.2639092994,"remaining_time":0.09515097188},
{"learn":[3.463037608],"iteration":735,"passed_time":0.2641700928,"remaining_time":0.09475666371},
{"learn":[3.45965637],"iteration":736,"passed_time":0.2644947616,"remaining_time":0.09438551194},
{"learn":[3.457275091],"iteration":737,"passed_time":0.2647794718,"remaining_time":0.0940003003},
{"learn":[3.455522955],"iteration":738,"passed_time":0.2650488903,"remaining_time":0.0936099599},
{"learn":[3.451270508],"iteration":739,"passed_time":0.2653547673,"remaining_time":0.09323275609},
{"learn":[3.450978947],"iteration":740,"passed_time":0.265599394,"remaining_time":0.09283433608},
{"learn":[3.450608492],"iteration":741,"passed_time":0.2658283538,"remaining_time":0.09243088314},
{"learn":[3.448122004],"iteration":742,"passed_time":0.2660637721,"remaining_time":0.09203013381},
{"learn":[3.445646714],"iteration":743,"passed_time":0.2663180238,"remaining_time":0.09163630925},
{"learn":[3.44411263],"iteration":744,"passed_time":0.2665615254,"remaining_time":0.09123917983},
{"learn":[3.443264164],"iteration":745,"passed_time":0.2668136521,"remaining_time":0.09084539896},
{"learn":[3.439521363],"iteration":746,"passed_time":0.2670453203,"remaining_time":0.09044506831},
{"learn":[3.436809225],"iteration":747,"passed_time":0.2672803635,"remaining_time":0.09004632567},
{"learn":[3.435509465],"iteration":748,"passed_time":0.2675486986,"remaining_time":0.08965917671},
{"learn":[3.434450277],"iteration":749,"passed_time":0.2677827835,"remaining_time":0.08926092784},
{"learn":[3.431786753],"iteration":750,"passed_time":0.2680104517,"remaining_time":0.08886098864},
{"learn":[3.430150302],"iteration":751,"passed_time":0.2682396199,"remaining_time":0.0884620023},
{"learn":[3.42696281],"iteration":752,"passed_time":0.2684850799,"remaining_time":0.08806881105},
{"learn":[3.426870334],"iteration":753,"passed_time":0.2686908312,"remaining_time":0.08766305634},
{"learn":[3.425200309],"iteration":754,"passed_time":0.2689179994,"remaining_time":0.08726478126},
{"learn":[3.423383783],"iteration":755,"passed_time":0.2691732094,"remaining_time":0.08687600939},
{"learn":[3.422752979],"iteration":756,"passed_time":0.2694192944,"remaining_time":0.08648466122},
{"learn":[3.420845924],"iteration":757,"passed_time":0.2696385875,"remaining_time":0.08608514272},
{"learn":[3.418917862],"iteration":758,"passed_time":0.2698843808,"remaining_time":0.08569451355},
{"learn":[3.417095735],"iteration":759,"passed_time":0.270154091,"remaining_time":0.0853118182},
{"learn":[3.414391848],"iteration":760,"passed_time":0.2704130927,"remaining_time":0.08492605671},
{"learn":[3.41426711],"iteration":761,"passed_time":0.2706488026,"remaining_time":0.08453335304},
{"learn":[3.411976013],"iteration":762,"passed_time":0.2708588457,"remaining_time":0.08413308836},
{"learn":[3.408614844],"iteration":763,"passed_time":0.2710972639,"remaining_time":0.08374208676},
{"learn":[3.407906721],"iteration":764,"passed_time":0.2713267654,"remaining_time":0.08334874494},
{"learn":[3.407494015],"iteration":765,"passed_time":0.2715721837,"remaining_time":0.08296069321},
{"learn":[3.406287128],"iteration":766,"passed_time":0.2718299771,"remaining_time":0.08257677271},
{"learn":[3.404600442],"iteration":767,"passed_time":0.2720801455,"remaining_time":0.08219087727},
{"learn":[3.404012662],"iteration":768,"passed_time":0.2723023969,"remaining_time":0.08179694889},
{"learn":[3.400398762],"iteration":769,"passed_time":0.2725296068,"remaining_time":0.08140494748},
{"learn":[3.399737714],"iteration":770,"passed_time":0.2727404832,"remaining_time":0.08100852225},
{"learn":[3.399185251],"iteration":771,"passed_time":0.2729879848,"remaining_time":0.08062339449},
{"learn":[3.397245411],"iteration":772,"passed_time":0.2732257364,"remaining_time":0.0802357596},
{"learn":[3.396229831],"iteration":773,"passed_time":0.2734322795,"remaining_time":0.07983939943},
{"learn":[3.394002836],"iteration":774,"passed_time":0.2736579476,"remaining_time":0.07944908157},
{"learn":[3.389617243],"iteration":775,"passed_time":0.2738840741,"remaining_time":0.07905932037},
{"learn":[3.385426488],"iteration":776,"passed_time":0.274118534,"remaining_time":0.07867237206},
{"learn":[3.385072258],"iteration":777,"passed_time":0.2743404522,"remaining_time":0.078282237},
{"learn":[3.383842366],"iteration":778,"passed_time":0.2746245791,"remaining_time":0.07791018225},
{"learn":[3.380110746],"iteration":779,"passed_time":0.274857289,"remaining_time":0.07752385073},
{"learn":[3.378595218],"iteration":780,"passed_time":0.2750833738,"remaining_time":0.07713605488},
{"learn":[3.377371219],"iteration":781,"passed_time":0.2753045003,"remaining_time":0.07674729036},
{"learn":[3.375814782],"iteration":782,"passed_time":0.2755444185,"remaining_time":0.07636416197},
{"learn":[3.374195887],"iteration":783,"passed_time":0.2757719617,"remaining_time":0.07597798945},
{"learn":[3.373704309],"iteration":784,"passed_time":0.2760049633,"remaining_time":0.07559371605},
{"learn":[3.372971757],"iteration":785,"passed_time":0.2762281314,"remaining_time":0.07520715029},
{"learn":[3.371565136],"iteration":786,"passed_time":0.2764520912,"remaining_time":0.07482121402},
{"learn":[3.3700309],"iteration":787,"passed_time":0.2766652177,"remaining_time":0.0744327743},
{"learn":[3.368186663],"iteration":788,"passed_time":0.2768772191,"remaining_time":0.07404447811},
{"learn":[3.366710398],"iteration":789,"passed_time":0.2771107623,"remaining_time":0.07366235454},
{"learn":[3.364598042],"iteration":790,"passed_time":0.277364889,"remaining_time":0.07328604526},
{"learn":[3.36348442],"iteration":791,"passed_time":0.2776042239,"remaining_time":0.07290615982},
{"learn":[3.362001759],"iteration":792,"passed_time":0.2778523506,"remaining_time":0.07252892379},
{"learn":[3.361580401],"iteration":793,"passed_time":0.2780836021,"remaining_time":0.07214763481},
{"learn":[3.359543675],"iteration":794,"passed_time":0.2783248121,"remaining_time":0.07176929116},
{"learn":[3.35766119],"iteration":795,"passed_time":0.278572772,"remaining_time":0.07139302198},
{"learn":[3.354592969],"iteration":796,"passed_time":0.278811982,"remaining_time":0.0710148461},
{"learn":[3.350985986],"iteration":797,"passed_time":0.2790491919,"remaining_time":0.07063651223},
{"learn":[3.349589624],"iteration":798,"passed_time":0.2793118603,"remaining_time":0.07026493607},
{"learn":[3.349110856],"iteration":799,"passed_time":0.2795599453,"remaining_time":0.06988998632},
{"learn":[3.345315441],"iteration":800,"passed_time":0.2798159887,"remaining_time":0.06951733051},
{"learn":[3.34397474],"iteration":801,"passed_time":0.2800750737,"remaining_time":0.06914571645},
{"learn":[3.343800902],"iteration":802,"passed_time":0.2802958668,"remaining_time":0.0687649885},
{"learn":[3.342329465],"iteration":803,"passed_time":0.2805554936,"remaining_time":0.0683941253},
{"learn":[3.34220347],"iteration":804,"passed_time":0.2808219954,"remaining_time":0.06802520384},
{"learn":[3.341279219],"iteration":805,"passed_time":0.2810760804,"remaining_time":0.06765354788},
{"learn":[3.337329521],"iteration":806,"passed_time":0.2813238737,"remaining_time":0.06728067859},
{"learn":[3.336708453],"iteration":807,"passed_time":0.2815622919,"remaining_time":0.06690589116},
{"learn":[3.333252703],"iteration":808,"passed_time":0.2818056269,"remaining_time":0.06653260165},
{"learn":[3.332186769],"iteration":809,"passed_time":0.2820408785,"remaining_time":0.06615773692},
{"learn":[3.330594851],"iteration":810,"passed_time":0.28226963,"remaining_time":0.06578170169},
{"learn":[3.327867442],"iteration":811,"passed_time":0.2825118816,"remaining_time":0.06540915485},
{"learn":[3.327563111],"iteration":812,"passed_time":0.2827337164,"remaining_time":0.06503223244},
{"learn":[3.326308994],"iteration":813,"passed_time":0.2829710513,"remaining_time":0.06465923286},
{"learn":[3.326249879],"iteration":814,"passed_time":0.2832019279,"remaining_time":0.06428510019},
{"learn":[3.322336238],"iteration":815,"passed_time":0.283427971,"remaining_time":0.06391022876},
{"learn":[3.320491154],"iteration":816,"passed_time":0.2836863061,"remaining_time":0.06354295473},
{"learn":[3.320434271],"iteration":817,"passed_time":0.2839593079,"remaining_time":0.06317921032},
{"learn":[3.319609638],"iteration":818,"passed_time":0.2842199346,"remaining_time":0.06281295259},
{"learn":[3.316182682],"iteration":819,"passed_time":0.2844523112,"remaining_time":0.06244075124},
{"learn":[3.313126612],"iteration":820,"passed_time":0.2846886878,"remaining_time":0.06206976262},
{"learn":[3.311222803],"iteration":821,"passed_time":0.2849116059,"remaining_time":0.06169618717},
{"learn":[3.309627335],"iteration":822,"passed_time":0.2851441075,"remaining_time":0.06132503891},
{"learn":[3.307974895],"iteration":823,"passed_time":0.2853800674,"remaining_time":0.06095496585},
{"learn":[3.307321505],"iteration":824,"passed_time":0.2856014439,"remaining_time":0.06058212445},
{"learn":[3.306759087],"iteration":825,"passed_time":0.2858563622,"remaining_time":0.06021671553},
{"learn":[3.30484037],"iteration":826,"passed_time":0.2861064472,"remaining_time":0.05985056272},
{"learn":[3.30201994],"iteration":827,"passed_time":0.2863592406,"remaining_time":0.05948525287},
{"learn":[3.299302297],"iteration":828,"passed_time":0.2865966588,"remaining_time":0.05911704301},
{"learn":[3.298132671],"iteration":829,"passed_time":0.2868493272,"remaining_time":0.05875227183},
{"learn":[3.296976183],"iteration":830,"passed_time":0.2870755787,"remaining_time":0.05838239807},
{"learn":[3.293144745],"iteration":831,"passed_time":0.2873219136,"remaining_time":0.05801692487},
{"learn":[3.290284404],"iteration":832,"passed_time":0.2875892071,"remaining_time":0.05765593948},
{"learn":[3.288285745],"iteration":833,"passed_time":0.2878340421,"remaining_time":0.05729070861},
{"learn":[3.286662667],"iteration":834,"passed_time":0.2880697936,"remaining_time":0.0569239712},
{"learn":[3.285692682],"iteration":835,"passed_time":0.2883112952,"remaining_time":0.05655867514},
{"learn":[3.284565611],"iteration":836,"passed_time":0.2885565885,"remaining_time":0.0561944133},
{"learn":[3.283897383],"iteration":837,"passed_time":0.2887915068,"remaining_time":0.05582842971},
{"learn":[3.280712855],"iteration":838,"passed_time":0.2890072165,"remaining_time":0.05545907254},
{"learn":[3.280468341],"iteration":839,"passed_time":0.2892513015,"remaining_time":0.055095486},
{"learn":[3.277814895],"iteration":840,"passed_time":0.2894519278,"remaining_time":0.05472396733},
{"learn":[3.276316385],"iteration":841,"passed_time":0.2896937628,"remaining_time":0.05436058731},
{"learn":[3.27557063],"iteration":842,"passed_time":0.2899308477,"remaining_time":0.05399661102},
{"learn":[3.27499628],"iteration":843,"passed_time":0.2901528908,"remaining_time":0.05363015518},
{"learn":[3.273569958],"iteration":844,"passed_time":0.2904146842,"remaining_time":0.05327133261},
{"learn":[3.269665595],"iteration":845,"passed_time":0.2906674776,"remaining_time":0.05291110112},
{"learn":[3.267984685],"iteration":846,"passed_time":0.2909002708,"remaining_time":0.05254751055},
{"learn":[3.267702508],"iteration":847,"passed_time":0.2911398557,"remaining_time":0.05218544584},
{"learn":[3.266671924],"iteration":848,"passed_time":0.2913952324,"remaining_time":0.05182647833},
{"learn":[3.265359825],"iteration":849,"passed_time":0.2916218173,"remaining_time":0.05146267364},
{"learn":[3.2618983],"iteration":850,"passed_time":0.2918632356,"remaining_time":0.0511017886},
{"learn":[3.260456253],"iteration":851,"passed_time":0.2921163206,"remaining_time":0.05074321062},
{"learn":[3.258389147],"iteration":852,"passed_time":0.2923703639,"remaining_time":0.05038504513},
{"learn":[3.258108469],"iteration":853,"passed_time":0.2925905321,"remaining_time":0.05002133218},
{"learn":[3.256424936],"iteration":854,"passed_time":0.2928282836,"remaining_time":0.04966093699},
{"learn":[3.254817983],"iteration":855,"passed_time":0.2930616185,"remaining_time":0.04930008536},
{"learn":[3.253898449],"iteration":856,"passed_time":0.2932889117,"remaining_time":0.04893852319},
{"learn":[3.253023652],"iteration":857,"passed_time":0.2935682052,"remaining_time":0.04858588012},
{"learn":[3.252845542],"iteration":858,"passed_time":0.2938008318,"remaining_time":0.04822574771},
{"learn":[3.252316026],"iteration":859,"passed_time":0.2940791253,"remaining_time":0.04787334598},
{"learn":[3.24975301],"iteration":860,"passed_time":0.2943281686,"remaining_time":0.04751639424},
{"learn":[3.249151075],"iteration":861,"passed_time":0.2945495451,"remaining_time":0.0471552636},
{"learn":[3.246257135],"iteration":862,"passed_time":0.2947950051,"remaining_time":0.04679828007},
{"learn":[3.243826471],"iteration":863,"passed_time":0.2950090482,"remaining_time":0.04643660943},
{"learn":[3.243190653],"iteration":864,"passed_time":0.2952802166,"remaining_time":0.04608419566},
{"learn":[3.24008797],"iteration":865,"passed_time":0.295533135,"remaining_time":0.0457291456},
{"learn":[3.240036811],"iteration":866,"passed_time":0.2957932201,"remaining_time":0.04537543053},
{"learn":[3.238676314],"iteration":867,"passed_time":0.2960554718,"remaining_time":0.04502226069},
{"learn":[3.237848782],"iteration":868,"passed_time":0.2963090568,"remaining_time":0.04466799361},
{"learn":[3.236405498],"iteration":869,"passed_time":0.2965646002,"remaining_time":0.0443142506},
{"learn":[3.233378068],"iteration":870,"passed_time":0.2967993101,"remaining_time":0.04395764753},
{"learn":[3.233169169],"iteration":871,"passed_time":0.2970495618,"remaining_time":0.0436036054},
{"learn":[3.232434885],"iteration":872,"passed_time":0.2972934384,"remaining_time":0.04324887363},
{"learn":[3.229978115],"iteration":873,"passed_time":0.2975186899,"remaining_time":0.04289171044},
{"learn":[3.229648848],"iteration":874,"passed_time":0.2977525248,"remaining_time":0.04253607497},
{"learn":[3.227208761],"iteration":875,"passed_time":0.2979665679,"remaining_time":0.042177916},
{"learn":[3.226258869],"iteration":876,"passed_time":0.2981911944,"remaining_time":0.04182157002},
{"learn":[3.225331995],"iteration":877,"passed_time":0.2984596545,"remaining_time":0.04147161486},
{"learn":[3.221968268],"iteration":878,"passed_time":0.2986781559,"remaining_time":0.041114968},
{"learn":[3.221166317],"iteration":879,"passed_time":0.2989294493,"remaining_time":0.04076310672},
{"learn":[3.220047503],"iteration":880,"passed_time":0.2991723259,"remaining_time":0.04041033687},
{"learn":[3.21982781],"iteration":881,"passed_time":0.2993840356,"remaining_time":0.04005364649},
{"learn":[3.216693405],"iteration":882,"passed_time":0.2996244539,"remaining_time":0.03970108846},
{"learn":[3.214798761],"iteration":883,"passed_time":0.2998467054,"remaining_time":0.03934640026},
{"learn":[3.214395085],"iteration":884,"passed_time":0.3000729152,"remaining_time":0.03899252571},
{"learn":[3.213470696],"iteration":885,"passed_time":0.3002981251,"remaining_time":0.03863881067},
{"learn":[3.211595017],"iteration":886,"passed_time":0.3005180015,"remaining_time":0.03828470594},
{"learn":[3.210965255],"iteration":887,"passed_time":0.300741128,"remaining_time":0.03793131344},
{"learn":[3.209413583],"iteration":888,"passed_time":0.3009897547,"remaining_time":0.03758139794},
{"learn":[3.208331683],"iteration":889,"passed_time":0.3012195479,"remaining_time":0.03722938232},
{"learn":[3.207110711],"iteration":890,"passed_time":0.3014355493,"remaining_time":0.03687595384},
{"learn":[3.204519413],"iteration":891,"passed_time":0.3016813009,"remaining_time":0.03652643554},
{"learn":[3.201421296],"iteration":892,"passed_time":0.3019365943,"remaining_time":0.03617829294},
{"learn":[3.200691259],"iteration":893,"passed_time":0.3021699292,"remaining_time":0.03582775447},
{"learn":[3.200485067],"iteration":894,"passed_time":0.3023867223,"remaining_time":0.03547553725},
{"learn":[3.197467568],"iteration":895,"passed_time":0.3026488491,"remaining_time":0.03512888427},
{"learn":[3.195838544],"iteration":896,"passed_time":0.3028675172,"remaining_time":0.03477742951},
{"learn":[3.195671746],"iteration":897,"passed_time":0.3031161855,"remaining_time":0.03442967809},
{"learn":[3.194213094],"iteration":898,"passed_time":0.3033592705,"remaining_time":0.03408151982},
{"learn":[3.192884691],"iteration":899,"passed_time":0.3035951054,"remaining_time":0.03373278948},
{"learn":[3.188364239],"iteration":900,"passed_time":0.3038508154,"remaining_time":0.03338649359},
{"learn":[3.185219478],"iteration":901,"passed_time":0.304091817,"remaining_time":0.03303880052},
{"learn":[3.184120387],"iteration":902,"passed_time":0.3043197352,"remaining_time":0.03268993833},
{"learn":[3.183725321],"iteration":903,"passed_time":0.304546695,"remaining_time":0.03234124195},
{"learn":[3.181264554],"iteration":904,"passed_time":0.3047679465,"remaining_time":0.03199221538},
{"learn":[3.180741589],"iteration":905,"passed_time":0.3049944897,"remaining_time":0.0316440199},
{"learn":[3.179782639],"iteration":906,"passed_time":0.3052168245,"remaining_time":0.03129566117},
{"learn":[3.176377564],"iteration":907,"passed_time":0.3054551594,"remaining_time":0.03094920117},
{"learn":[3.174078182],"iteration":908,"passed_time":0.3056898693,"remaining_time":0.03060261618},
{"learn":[3.171242379],"iteration":909,"passed_time":0.3059342459,"remaining_time":0.03025723311},
{"learn":[3.170421012],"iteration":910,"passed_time":0.3061832476,"remaining_time":0.02991252364},
{"learn":[3.170087224],"iteration":911,"passed_time":0.3064356659,"remaining_time":0.02956835373},
{"learn":[3.167303059],"iteration":912,"passed_time":0.3066899593,"remaining_time":0.02922456348},
{"learn":[3.16705966],"iteration":913,"passed_time":0.3069223775,"remaining_time":0.0288789108},
{"learn":[3.165667683],"iteration":914,"passed_time":0.3071815042,"remaining_time":0.02853598673},
{"learn":[3.164689733],"iteration":915,"passed_time":0.3074285059,"remaining_time":0.02819213373},
{"learn":[3.163311455],"iteration":916,"passed_time":0.3076561741,"remaining_time":0.02784674204},
{"learn":[3.159425016],"iteration":917,"passed_time":0.3078771755,"remaining_time":0.02750101132},
{"learn":[3.159327058],"iteration":918,"passed_time":0.3081128854,"remaining_time":0.02715684845},
{"learn":[3.15819426],"iteration":919,"passed_time":0.308338762,"remaining_time":0.02681206626},
{"learn":[3.157086603],"iteration":920,"passed_time":0.3085784719,"remaining_time":0.02646872886},
{"learn":[3.153354154],"iteration":921,"passed_time":0.3088056817,"remaining_time":0.02612455876},
{"learn":[3.153261317],"iteration":922,"passed_time":0.3090278499,"remaining_time":0.0257802215},
{"learn":[3.153168454],"iteration":923,"passed_time":0.309251893,"remaining_time":0.02543630289},
{"learn":[3.152080399],"iteration":924,"passed_time":0.309503978,"remaining_time":0.02509491714},
{"learn":[3.151635144],"iteration":925,"passed_time":0.309753188,"remaining_time":0.02475349451},
{"learn":[3.147762655],"iteration":926,"passed_time":0.3100354399,"remaining_time":0.02441487283},
{"learn":[3.147172317],"iteration":927,"passed_time":0.3102764832,"remaining_time":0.02407317542},
{"learn":[3.146254125],"iteration":928,"passed_time":0.3105099847,"remaining_time":0.02373111832},
{"learn":[3.144869828],"iteration":929,"passed_time":0.3107409446,"remaining_time":0.02338910336},
{"learn":[3.143466218],"iteration":930,"passed_time":0.310994488,"remaining_time":0.02304900072},
{"learn":[3.141919643],"iteration":931,"passed_time":0.3112429896,"remaining_time":0.02270871598},
{"learn":[3.141054135],"iteration":932,"passed_time":0.3115637834,"remaining_time":0.02237381939},
{"learn":[3.139390417],"iteration":933,"passed_time":0.3118250352,"remaining_time":0.02203474553},
{"learn":[3.139025283],"iteration":934,"passed_time":0.3120741618,"remaining_time":0.02169499521},
{"learn":[3.137824183],"iteration":935,"passed_time":0.3123201635,"remaining_time":0.02135522485},
{"learn":[3.135620453],"iteration":936,"passed_time":0.3125429983,"remaining_time":0.021014097},
{"learn":[3.13443178],"iteration":937,"passed_time":0.312794625,"remaining_time":0.02067512446},
{"learn":[3.132765713],"iteration":938,"passed_time":0.3130350849,"remaining_time":0.02033561254},
{"learn":[3.131434124],"iteration":939,"passed_time":0.3133028783,"remaining_time":0.01999805606},
{"learn":[3.128384262],"iteration":940,"passed_time":0.3135457966,"remaining_time":0.01965908821},
{"learn":[3.128120455],"iteration":941,"passed_time":0.3137852982,"remaining_time":0.0193201139},
{"learn":[3.126314615],"iteration":942,"passed_time":0.3140406749,"remaining_time":0.01898231015},
{"learn":[3.125409666],"iteration":943,"passed_time":0.3142716765,"remaining_time":0.01864323504},
{"learn":[3.123072589],"iteration":944,"passed_time":0.3144953863,"remaining_time":0.01830396428},
{"learn":[3.122921099],"iteration":945,"passed_time":0.3147366796,"remaining_time":0.01796594154},
{"learn":[3.122182662],"iteration":946,"passed_time":0.3149652228,"remaining_time":0.01762740951},
{"learn":[3.120040951],"iteration":947,"passed_time":0.3152070577,"remaining_time":0.01728983861},
{"learn":[3.118767799],"iteration":948,"passed_time":0.3154357259,"remaining_time":0.01695176188},
{"learn":[3.118203218],"iteration":949,"passed_time":0.3157482696,"remaining_time":0.01661832998},
{"learn":[3.116343362],"iteration":950,"passed_time":0.3159954379,"remaining_time":0.01628157356},
{"learn":[3.11480829],"iteration":951,"passed_time":0.316210231,"remaining_time":0.01594337299},
{"learn":[3.112607903],"iteration":952,"passed_time":0.3164587327,"remaining_time":0.01560709385},
{"learn":[3.111661241],"iteration":953,"passed_time":0.3167149427,"remaining_time":0.0152713704},
{"learn":[3.110249676],"iteration":954,"passed_time":0.316949111,"remaining_time":0.01493477486},
{"learn":[3.107333579],"iteration":955,"passed_time":0.3172024043,"remaining_time":0.01459927384},
{"learn":[3.107149851],"iteration":956,"passed_time":0.3174251141,"remaining_time":0.01426257044},
{"learn":[3.106867336],"iteration":957,"passed_time":0.3176770741,"remaining_time":0.01392738738},
{"learn":[3.10364681],"iteration":958,"passed_time":0.3179144091,"remaining_time":0.01359175263},
{"learn":[3.102703811],"iteration":959,"passed_time":0.3181309522,"remaining_time":0.01325545634},
{"learn":[3.101469264],"iteration":960,"passed_time":0.3183607037,"remaining_time":0.01291994531},
{"learn":[3.09863569],"iteration":961,"passed_time":0.3185937053,"remaining_time":0.01258478254},
{"learn":[3.09645939],"iteration":962,"passed_time":0.3188384986,"remaining_time":0.01225028499},
{"learn":[3.096240186],"iteration":963,"passed_time":0.3190541667,"remaining_time":0.01191488589},
{"learn":[3.094838828],"iteration":964,"passed_time":0.3192725014,"remaining_time":0.01157983166},
{"learn":[3.094176802],"iteration":965,"passed_time":0.3195086697,"remaining_time":0.01124564676},
{"learn":[3.093182279],"iteration":966,"passed_time":0.3197409212,"remaining_time":0.01091153092},
{"learn":[3.090150687],"iteration":967,"passed_time":0.3199677561,"remaining_time":0.01057744648},
{"learn":[3.088612829],"iteration":968,"passed_time":0.320204841,"remaining_time":0.01024391132},
{"learn":[3.087153684],"iteration":969,"passed_time":0.3204459676,"remaining_time":0.009910700029},
{"learn":[3.085866843],"iteration":970,"passed_time":0.3206686357,"remaining_time":0.009577127123},
{"learn":[3.082669094],"iteration":971,"passed_time":0.3208964706,"remaining_time":0.009243931252},
{"learn":[3.081047548],"iteration":972,"passed_time":0.3211750558,"remaining_time":0.008912360232},
{"learn":[3.079684322],"iteration":973,"passed_time":0.321407849,"remaining_time":0.008579675641},
{"learn":[3.07613431],"iteration":974,"passed_time":0.321652559,"remaining_time":0.008247501512},
{"learn":[3.074005935],"iteration":975,"passed_time":0.3218873522,"remaining_time":0.007915262759},
{"learn":[3.072988853],"iteration":976,"passed_time":0.3221446872,"remaining_time":0.007583754152},
{"learn":[3.072344268],"iteration":977,"passed_time":0.3223768971,"remaining_time":0.007251832042},
{"learn":[3.070654438],"iteration":978,"passed_time":0.3226208571,"remaining_time":0.006920365678},
{"learn":[3.069724506],"iteration":979,"passed_time":0.3228784421,"remaining_time":0.006589355962},
{"learn":[3.067763166],"iteration":980,"passed_time":0.3231296521,"remaining_time":0.006258372467},
{"learn":[3.066737893],"iteration":981,"passed_time":0.3233701537,"remaining_time":0.00592735516},
{"learn":[3.065248174],"iteration":982,"passed_time":0.3236312388,"remaining_time":0.005596877985},
{"learn":[3.063186837],"iteration":983,"passed_time":0.3238662404,"remaining_time":0.00526611773},
{"learn":[3.062880371],"iteration":984,"passed_time":0.3240955752,"remaining_time":0.004935465613},
{"learn":[3.061288645],"iteration":985,"passed_time":0.32431466,"remaining_time":0.004604873469},
{"learn":[3.059970575],"iteration":986,"passed_time":0.32455462,"remaining_time":0.004274782228},
{"learn":[3.059576341],"iteration":987,"passed_time":0.3248268301,"remaining_time":0.003945265143},
{"learn":[3.058175919],"iteration":988,"passed_time":0.3250677067,"remaining_time":0.003615515444},
{"learn":[3.056830702],"iteration":989,"passed_time":0.3253135,"remaining_time":0.00328599495},
{"learn":[3.056336579],"iteration":990,"passed_time":0.32556971,"remaining_time":0.002956738033},
{"learn":[3.055810414],"iteration":991,"passed_time":0.32580967,"remaining_time":0.002627497339},
{"learn":[3.055476518],"iteration":992,"passed_time":0.3260236714,"remaining_time":0.002298253474},
{"learn":[3.053331734],"iteration":993,"passed_time":0.326258423,"remaining_time":0.001969366738},
{"learn":[3.050890374],"iteration":994,"passed_time":0.3265331748,"remaining_time":0.001640870225},
{"learn":[3.04972623],"iteration":995,"passed_time":0.3268303434,"remaining_time":0.00131257166},
{"learn":[3.047217327],"iteration":996,"passed_time":0.3270913452,"remaining_time":0.0009842267157},
{"learn":[3.047155483],"iteration":997,"passed_time":0.3273883888,"remaining_time":0.0006560889556},
{"learn":[3.04430671],"iteration":998,"passed_time":0.3276510989,"remaining_time":0.000327979078},
{"learn":[3.042664195],"iteration":999,"passed_time":0.3279020173,"remaining_time":0}
]}